Workbook

Sheet Léeme
A1: Chambea · Matriz de transiciones entre ocupaciones
A2: Innovathon Ulima x Tether 2026 · Reto del MTPE · Datos ilustrativos para el prototipo
A4: ¿Para qué sirve? | B4: No existe una base oficial de transiciones entre ocupaciones: identificarlas es parte del reto. Esta matriz las construye a partir de las competencias que comparten las ocupaciones, con sustento técnico y mecanismos de validación.
A5: Idea central | B5: Si soy cajera, ya desarrollé habilidades como cobrar sin errores, manejar medios de pago, atender al cliente y tener paciencia. Esas mismas habilidades las pide un vendedor de tienda. Por eso «Vendedor/a de tienda» está cerca de «Cajero/a», y «Auxiliar de almacén» está lejos.
A6: Cómo se calcula | B6: Proximidad(A → B) = suma de pesos de las habilidades de B que A ya tiene ÷ suma de pesos de todas las habilidades de B. Pesos: logro 3 · habilidad 2 · conocimiento 2 · cualidad 1 (hoja «Supuestos»). Es la misma fórmula que usa la app.
A7: Pares más cercanos (con los pesos actuales) | B7: Personal de limpieza → Conserje / mantenimiento: 58% · Conserje / mantenimiento → Personal de limpieza: 58% · Vendedor/a de tienda → Cajero/a: 54% · Cajero/a → Vendedor/a de tienda: 50% · Reponedor/a y abastecedor/a → Auxiliar de almacén: 46% · Auxiliar de almacén → Reponedor/a y abastecedor/a: 46%
A8: Cómo leer las hojas | B8: «Resumen»: las 3 más cercanas y la más lejana de cada oficio. «Proximidad»: matriz 13 × 13 con colores. «Rutas por oficio»: de la más cercana a la más lejana, con lo que comparten y lo que les falta. «Matriz habilidades»: qué habilidades pide cada ocupación. «En común»: cuántas habilidades comparten. «Validación»: sustento técnico y plantilla para asesores. «Supuestos»: pesos y cortes que se pueden cambiar.
A9: Ojo: matriz vs. app | B9: La matriz compara el perfil típico de una ocupación con otra (7 habilidades cada una). En la app se compara el panal real de la persona, que suele tener más habilidades; por eso allí la cobertura suele ser mayor (ej.: Rosa tiene 6 de 7 para Vendedor/a de tienda).
A10: Datos | B10: 13 ocupaciones de nivel operativo (5 priorizadas por el MTPE + 8 para ampliar rutas) y 44 habilidades usadas, de un catálogo de 48. Todos son ilustrativos: se reemplazarán por los estándares de competencia del MTPE y la EDO 2026 sin cambiar el cálculo.
A11: Colores | B11: Celdas con texto azul = datos o supuestos que se pueden cambiar. Celdas amarillas (hoja Validación) = para que las llenen los asesores. Matrices: blanco = lejanas, amarillo = medias, verde = cercanas.

Sheet Supuestos
A1: Supuestos del cálculo
A2: Celdas en azul: se pueden cambiar. Todo el libro se recalcula solo.
A4: Dimensión del perfil (MTPE) | B4: Peso | C4: Qué significa
A5: Logro (competencia) | B5: 3 | C5: Lo que logra y cómo lo demuestra
A6: Habilidad | B6: 2 | C6: Lo que sabe hacer
A7: Conocimiento | B7: 2 | C7: Lo que sabe
A8: Cualidad | B8: 1 | C8: Cómo es
A9: Fuente de los pesos: motor de Chambea (shared/src/motor.ts, constante PESOS). Un logro pesa más porque es la prueba más fuerte; una cualidad pesa menos porque la comparten casi todos los trabajos.
A11: Clasificación de la cercanía (solo para esta matriz) | B11: Desde | C11: Lectura
A12: Cercana | B12: 0.4 | C12: Comparten buena parte del perfil: la transición es natural.
A13: Media | B13: 0.2 | C13: Comparten algo: con un curso corto se acercan.
A14: Lejana | B14: 0 | C14: Comparten poco o nada: haría falta empezar casi de cero.
A15: Supuesto del equipo: estos cortes ordenan ocupación contra ocupación usando solo las 7 habilidades típicas de cada una. En la app, la cobertura se calcula con el panal real de la persona (que suele tener más habilidades), y ahí se usan otros cortes: 85 % o más = puede postular; 50 % a 85 % = curso; menos de 50 % = asesor.

Sheet Resumen
A1: Resumen: las ocupaciones más próximas y más lejanas de cada oficio
A2: Para leer de un vistazo. El detalle (qué comparten y qué les falta) está en «Rutas por oficio».
A4: Oficio de hoy | B4: Más cercana 1 | C4: % | D4: Más cercana 2 | E4: % | F4: Más cercana 3 | G4: % | H4: Más lejana | I4: % | J4: Lo que comparte con la más cercana
A5: Cajero/a | B5: Vendedor/a de tienda | C5: =INDEX(Proximidad!$C$6:$O$18,MATCH($A5,Proximidad!$B$6:$B$18,0),MATCH(B5,Proximidad!$C$5:$O$5,0)) -> 0.5 | D5: Mozo/a de restaurante | E5: =INDEX(Proximidad!$C$6:$O$18,MATCH($A5,Proximidad!$B$6:$B$18,0),MATCH(D5,Proximidad!$C$5:$O$5,0)) -> 0.38461538 | F5: Repartidor/a | G5: =INDEX(Proximidad!$C$6:$O$18,MATCH($A5,Proximidad!$B$6:$B$18,0),MATCH(F5,Proximidad!$C$5:$O$5,0)) -> 0.25 | H5: Reponedor/a y abastecedor/a | I5: =INDEX(Proximidad!$C$6:$O$18,MATCH($A5,Proximidad!$B$6:$B$18,0),MATCH(H5,Proximidad!$C$5:$O$5,0)) -> 0 | J5: Atención al cliente, Medios de pago, Cobro en caja, Paciencia
A6: Vendedor/a de tienda | B6: Cajero/a | C6: =INDEX(Proximidad!$C$6:$O$18,MATCH($A6,Proximidad!$B$6:$B$18,0),MATCH(B6,Proximidad!$C$5:$O$5,0)) -> 0.53846154 | D6: Mozo/a de restaurante | E6: =INDEX(Proximidad!$C$6:$O$18,MATCH($A6,Proximidad!$B$6:$B$18,0),MATCH(D6,Proximidad!$C$5:$O$5,0)) -> 0.38461538 | F6: Asesor/a de atención al cliente | G6: =INDEX(Proximidad!$C$6:$O$18,MATCH($A6,Proximidad!$B$6:$B$18,0),MATCH(F6,Proximidad!$C$5:$O$5,0)) -> 0.28571429 | H6: Personal de limpieza | I6: =INDEX(Proximidad!$C$6:$O$18,MATCH($A6,Proximidad!$B$6:$B$18,0),MATCH(H6,Proximidad!$C$5:$O$5,0)) -> 0 | J6: Cobro en caja, Medios de pago, Atención al cliente, Paciencia
A7: Reponedor/a y abastecedor/a | B7: Auxiliar de almacén | C7: =INDEX(Proximidad!$C$6:$O$18,MATCH($A7,Proximidad!$B$6:$B$18,0),MATCH(B7,Proximidad!$C$5:$O$5,0)) -> 0.46153846 | D7: Operario/a de producción | E7: =INDEX(Proximidad!$C$6:$O$18,MATCH($A7,Proximidad!$B$6:$B$18,0),MATCH(D7,Proximidad!$C$5:$O$5,0)) -> 0.18181818 | F7: Vendedor/a de tienda | G7: =INDEX(Proximidad!$C$6:$O$18,MATCH($A7,Proximidad!$B$6:$B$18,0),MATCH(F7,Proximidad!$C$5:$O$5,0)) -> 0.14285714 | H7: Mozo/a de restaurante | I7: =INDEX(Proximidad!$C$6:$O$18,MATCH($A7,Proximidad!$B$6:$B$18,0),MATCH(H7,Proximidad!$C$5:$O$5,0)) -> 0 | J7: Recepción de mercadería, Control de inventario, Organización y orden, Resistencia física
A8: Auxiliar administrativo/a | B8: Asesor/a de atención al cliente | C8: =INDEX(Proximidad!$C$6:$O$18,MATCH($A8,Proximidad!$B$6:$B$18,0),MATCH(B8,Proximidad!$C$5:$O$5,0)) -> 0.28571429 | D8: Conserje / mantenimiento | E8: =INDEX(Proximidad!$C$6:$O$18,MATCH($A8,Proximidad!$B$6:$B$18,0),MATCH(D8,Proximidad!$C$5:$O$5,0)) -> 0.25 | F8: Auxiliar de almacén | G8: =INDEX(Proximidad!$C$6:$O$18,MATCH($A8,Proximidad!$B$6:$B$18,0),MATCH(F8,Proximidad!$C$5:$O$5,0)) -> 0.23076923 | H8: Vendedor/a de tienda | I8: =INDEX(Proximidad!$C$6:$O$18,MATCH($A8,Proximidad!$B$6:$B$18,0),MATCH(H8,Proximidad!$C$5:$O$5,0)) -> 0 | J8: Registro de datos, Computación básica
A9: Personal de limpieza | B9: Conserje / mantenimiento | C9: =INDEX(Proximidad!$C$6:$O$18,MATCH($A9,Proximidad!$B$6:$B$18,0),MATCH(B9,Proximidad!$C$5:$O$5,0)) -> 0.58333333 | D9: Operario/a de producción | E9: =INDEX(Proximidad!$C$6:$O$18,MATCH($A9,Proximidad!$B$6:$B$18,0),MATCH(D9,Proximidad!$C$5:$O$5,0)) -> 0.27272727 | F9: Repartidor/a | G9: =INDEX(Proximidad!$C$6:$O$18,MATCH($A9,Proximidad!$B$6:$B$18,0),MATCH(F9,Proximidad!$C$5:$O$5,0)) -> 0.25 | H9: Vendedor/a de tienda | I9: =INDEX(Proximidad!$C$6:$O$18,MATCH($A9,Proximidad!$B$6:$B$18,0),MATCH(H9,Proximidad!$C$5:$O$5,0)) -> 0 | J9: Seguridad en el trabajo, Honestidad, Puntualidad, Ambientes impecables
A10: Ayudante de cocina | B10: Cuidador/a de personas | C10: =INDEX(Proximidad!$C$6:$O$18,MATCH($A10,Proximidad!$B$6:$B$18,0),MATCH(B10,Proximidad!$C$5:$O$5,0)) -> 0.33333333 | D10: Repartidor/a | E10: =INDEX(Proximidad!$C$6:$O$18,MATCH($A10,Proximidad!$B$6:$B$18,0),MATCH(D10,Proximidad!$C$5:$O$5,0)) -> 0.25 | F10: Auxiliar de almacén | G10: =INDEX(Proximidad!$C$6:$O$18,MATCH($A10,Proximidad!$B$6:$B$18,0),MATCH(F10,Proximidad!$C$5:$O$5,0)) -> 0.23076923 | H10: Vendedor/a de tienda | I10: =INDEX(Proximidad!$C$6:$O$18,MATCH($A10,Proximidad!$B$6:$B$18,0),MATCH(H10,Proximidad!$C$5:$O$5,0)) -> 0 | J10: Higiene de alimentos, Cocina
A11: Mozo/a de restaurante | B11: Cajero/a | C11: =INDEX(Proximidad!$C$6:$O$18,MATCH($A11,Proximidad!$B$6:$B$18,0),MATCH(B11,Proximidad!$C$5:$O$5,0)) -> 0.38461538 | D11: Vendedor/a de tienda | E11: =INDEX(Proximidad!$C$6:$O$18,MATCH($A11,Proximidad!$B$6:$B$18,0),MATCH(D11,Proximidad!$C$5:$O$5,0)) -> 0.35714286 | F11: Cuidador/a de personas | G11: =INDEX(Proximidad!$C$6:$O$18,MATCH($A11,Proximidad!$B$6:$B$18,0),MATCH(F11,Proximidad!$C$5:$O$5,0)) -> 0.33333333 | H11: Reponedor/a y abastecedor/a | I11: =INDEX(Proximidad!$C$6:$O$18,MATCH($A11,Proximidad!$B$6:$B$18,0),MATCH(H11,Proximidad!$C$5:$O$5,0)) -> 0 | J11: Cobro en caja, Atención al cliente, Paciencia
A12: Auxiliar de almacén | B12: Reponedor/a y abastecedor/a | C12: =INDEX(Proximidad!$C$6:$O$18,MATCH($A12,Proximidad!$B$6:$B$18,0),MATCH(B12,Proximidad!$C$5:$O$5,0)) -> 0.46153846 | D12: Operario/a de producción | E12: =INDEX(Proximidad!$C$6:$O$18,MATCH($A12,Proximidad!$B$6:$B$18,0),MATCH(D12,Proximidad!$C$5:$O$5,0)) -> 0.36363636 | F12: Conserje / mantenimiento | G12: =INDEX(Proximidad!$C$6:$O$18,MATCH($A12,Proximidad!$B$6:$B$18,0),MATCH(F12,Proximidad!$C$5:$O$5,0)) -> 0.33333333 | H12: Vendedor/a de tienda | I12: =INDEX(Proximidad!$C$6:$O$18,MATCH($A12,Proximidad!$B$6:$B$18,0),MATCH(H12,Proximidad!$C$5:$O$5,0)) -> 0 | J12: Control de inventario, Recepción de mercadería, Organización y orden, Resistencia física
A13: Repartidor/a | B13: Auxiliar de almacén | C13: =INDEX(Proximidad!$C$6:$O$18,MATCH($A13,Proximidad!$B$6:$B$18,0),MATCH(B13,Proximidad!$C$5:$O$5,0)) -> 0.30769231 | D13: Personal de limpieza | E13: =INDEX(Proximidad!$C$6:$O$18,MATCH($A13,Proximidad!$B$6:$B$18,0),MATCH(D13,Proximidad!$C$5:$O$5,0)) -> 0.25 | F13: Ayudante de cocina | G13: =INDEX(Proximidad!$C$6:$O$18,MATCH($A13,Proximidad!$B$6:$B$18,0),MATCH(F13,Proximidad!$C$5:$O$5,0)) -> 0.23076923 | H13: Asesor/a de atención al cliente | I13: =INDEX(Proximidad!$C$6:$O$18,MATCH($A13,Proximidad!$B$6:$B$18,0),MATCH(H13,Proximidad!$C$5:$O$5,0)) -> 0 | J13: Resistencia física, Pedidos a tiempo
A14: Operario/a de producción | B14: Auxiliar de almacén | C14: =INDEX(Proximidad!$C$6:$O$18,MATCH($A14,Proximidad!$B$6:$B$18,0),MATCH(B14,Proximidad!$C$5:$O$5,0)) -> 0.30769231 | D14: Conserje / mantenimiento | E14: =INDEX(Proximidad!$C$6:$O$18,MATCH($A14,Proximidad!$B$6:$B$18,0),MATCH(D14,Proximidad!$C$5:$O$5,0)) -> 0.25 | F14: Personal de limpieza | G14: =INDEX(Proximidad!$C$6:$O$18,MATCH($A14,Proximidad!$B$6:$B$18,0),MATCH(F14,Proximidad!$C$5:$O$5,0)) -> 0.25 | H14: Vendedor/a de tienda | I14: =INDEX(Proximidad!$C$6:$O$18,MATCH($A14,Proximidad!$B$6:$B$18,0),MATCH(H14,Proximidad!$C$5:$O$5,0)) -> 0 | J14: Organización y orden, Resistencia física, Seguridad en el trabajo
A15: Asesor/a de atención al cliente | B15: Auxiliar administrativo/a | C15: =INDEX(Proximidad!$C$6:$O$18,MATCH($A15,Proximidad!$B$6:$B$18,0),MATCH(B15,Proximidad!$C$5:$O$5,0)) -> 0.30769231 | D15: Vendedor/a de tienda | E15: =INDEX(Proximidad!$C$6:$O$18,MATCH($A15,Proximidad!$B$6:$B$18,0),MATCH(D15,Proximidad!$C$5:$O$5,0)) -> 0.28571429 | F15: Mozo/a de restaurante | G15: =INDEX(Proximidad!$C$6:$O$18,MATCH($A15,Proximidad!$B$6:$B$18,0),MATCH(F15,Proximidad!$C$5:$O$5,0)) -> 0.23076923 | H15: Reponedor/a y abastecedor/a | I15: =INDEX(Proximidad!$C$6:$O$18,MATCH($A15,Proximidad!$B$6:$B$18,0),MATCH(H15,Proximidad!$C$5:$O$5,0)) -> 0 | J15: Registro de datos, Computación básica
A16: Cuidador/a de personas | B16: Ayudante de cocina | C16: =INDEX(Proximidad!$C$6:$O$18,MATCH($A16,Proximidad!$B$6:$B$18,0),MATCH(B16,Proximidad!$C$5:$O$5,0)) -> 0.30769231 | D16: Mozo/a de restaurante | E16: =INDEX(Proximidad!$C$6:$O$18,MATCH($A16,Proximidad!$B$6:$B$18,0),MATCH(D16,Proximidad!$C$5:$O$5,0)) -> 0.30769231 | F16: Conserje / mantenimiento | G16: =INDEX(Proximidad!$C$6:$O$18,MATCH($A16,Proximidad!$B$6:$B$18,0),MATCH(F16,Proximidad!$C$5:$O$5,0)) -> 0.16666667 | H16: Reponedor/a y abastecedor/a | I16: =INDEX(Proximidad!$C$6:$O$18,MATCH($A16,Proximidad!$B$6:$B$18,0),MATCH(H16,Proximidad!$C$5:$O$5,0)) -> 0 | J16: Cocina, Higiene de alimentos
A17: Conserje / mantenimiento | B17: Personal de limpieza | C17: =INDEX(Proximidad!$C$6:$O$18,MATCH($A17,Proximidad!$B$6:$B$18,0),MATCH(B17,Proximidad!$C$5:$O$5,0)) -> 0.58333333 | D17: Auxiliar de almacén | E17: =INDEX(Proximidad!$C$6:$O$18,MATCH($A17,Proximidad!$B$6:$B$18,0),MATCH(D17,Proximidad!$C$5:$O$5,0)) -> 0.30769231 | F17: Operario/a de producción | G17: =INDEX(Proximidad!$C$6:$O$18,MATCH($A17,Proximidad!$B$6:$B$18,0),MATCH(F17,Proximidad!$C$5:$O$5,0)) -> 0.27272727 | H17: Vendedor/a de tienda | I17: =INDEX(Proximidad!$C$6:$O$18,MATCH($A17,Proximidad!$B$6:$B$18,0),MATCH(H17,Proximidad!$C$5:$O$5,0)) -> 0 | J17: Seguridad en el trabajo, Honestidad, Puntualidad, Ambientes impecables
A19: Cuando varias ocupaciones empatan en 0 % como «más lejana», se muestra la primera por orden alfabético: ninguna comparte habilidades típicas con el oficio de hoy.

Sheet Matriz habilidades
A1: Matriz Ocupación × Habilidades
A2: 1 = la ocupación pide esa habilidad (dato de data/ocupaciones.json). Cada ocupación pide 7. Datos ilustrativos, a reemplazar por los estándares de competencia del MTPE.
A5: Id | B5: Habilidad | C5: Cómo lo diría la persona | D5: Dimensión | E5: Peso | F5: Cajero/a | G5: Vendedor/a de tienda | H5: Reponedor/a y abastecedor/a | I5: Auxiliar administrativo/a | J5: Personal de limpieza | K5: Ayudante de cocina | L5: Mozo/a de restaurante | M5: Auxiliar de almacén | N5: Repartidor/a | O5: Operario/a de producción | P5: Asesor/a de atención al cliente | Q5: Cuidador/a de personas | R5: Conserje / mantenimiento | S5: N.º de ocupaciones que la piden
A6: con_documentos_comerciales | B6: Documentos comerciales | C6: Conozco boletas, facturas y guías | D6: Conocimiento | E6: =INDEX(Supuestos!$B$5:$B$8,MATCH(D6,Supuestos!$A$5:$A$8,0)) -> 2 | I6: 1 | S6: =COUNT(F6:R6) -> 1
A7: con_higiene_alimentos | B7: Higiene de alimentos | C7: Sé manejar alimentos con higiene | D7: Conocimiento | E7: =INDEX(Supuestos!$B$5:$B$8,MATCH(D7,Supuestos!$A$5:$A$8,0)) -> 2 | K7: 1 | Q7: 1 | S7: =COUNT(F7:R7) -> 2
A8: con_manejo_dinero | B8: Manejo de dinero | C8: Manejo plata sin que falte nada | D8: Conocimiento | E8: =INDEX(Supuestos!$B$5:$B$8,MATCH(D8,Supuestos!$A$5:$A$8,0)) -> 2 | N8: 1 | S8: =COUNT(F8:R8) -> 1
A9: con_medios_pago | B9: Medios de pago | C9: Sé cobrar con efectivo, tarjeta, Yape o Plin | D9: Conocimiento | E9: =INDEX(Supuestos!$B$5:$B$8,MATCH(D9,Supuestos!$A$5:$A$8,0)) -> 2 | F9: 1 | G9: 1 | S9: =COUNT(F9:R9) -> 2
A10: con_productos_limpieza | B10: Productos de limpieza | C10: Sé qué productos usar y cuáles no se mezclan | D10: Conocimiento | E10: =INDEX(Supuestos!$B$5:$B$8,MATCH(D10,Supuestos!$A$5:$A$8,0)) -> 2 | J10: 1 | S10: =COUNT(F10:R10) -> 1
A11: con_seguridad_trabajo | B11: Seguridad en el trabajo | C11: Sé trabajar sin ponerme en riesgo | D11: Conocimiento | E11: =INDEX(Supuestos!$B$5:$B$8,MATCH(D11,Supuestos!$A$5:$A$8,0)) -> 2 | J11: 1 | M11: 1 | O11: 1 | R11: 1 | S11: =COUNT(F11:R11) -> 4
A12: con_ubicacion_productos | B12: Ubicación de productos | C12: Sé dónde va cada cosa y qué vence primero | D12: Conocimiento | E12: =INDEX(Supuestos!$B$5:$B$8,MATCH(D12,Supuestos!$A$5:$A$8,0)) -> 2 | H12: 1 | S12: =COUNT(F12:R12) -> 1
A13: hab_archivo | B13: Archivo de documentos | C13: Ordeno y archivo papeles | D13: Habilidad | E13: =INDEX(Supuestos!$B$5:$B$8,MATCH(D13,Supuestos!$A$5:$A$8,0)) -> 2 | I13: 1 | S13: =COUNT(F13:R13) -> 1
A14: hab_atencion_cliente | B14: Atención al cliente | C14: Atiendo bien a la gente | D14: Habilidad | E14: =INDEX(Supuestos!$B$5:$B$8,MATCH(D14,Supuestos!$A$5:$A$8,0)) -> 2 | F14: 1 | G14: 1 | L14: 1 | N14: 1 | S14: =COUNT(F14:R14) -> 4
A15: hab_atencion_telefonica | B15: Atención telefónica | C15: Atiendo llamadas y mensajes | D15: Habilidad | E15: =INDEX(Supuestos!$B$5:$B$8,MATCH(D15,Supuestos!$A$5:$A$8,0)) -> 2 | P15: 1 | S15: =COUNT(F15:R15) -> 1
A16: hab_cobro_caja | B16: Cobro en caja | C16: Cobro rápido y sin equivocarme | D16: Habilidad | E16: =INDEX(Supuestos!$B$5:$B$8,MATCH(D16,Supuestos!$A$5:$A$8,0)) -> 2 | F16: 1 | G16: 1 | L16: 1 | S16: =COUNT(F16:R16) -> 3
A17: hab_cocina_basica | B17: Cocina | C17: Sé cocinar y preparar alimentos | D17: Habilidad | E17: =INDEX(Supuestos!$B$5:$B$8,MATCH(D17,Supuestos!$A$5:$A$8,0)) -> 2 | K17: 1 | Q17: 1 | S17: =COUNT(F17:R17) -> 2
A18: hab_ofimatica_basica | B18: Computación básica | C18: Manejo la computadora y Excel básico | D18: Habilidad | E18: =INDEX(Supuestos!$B$5:$B$8,MATCH(D18,Supuestos!$A$5:$A$8,0)) -> 2 | I18: 1 | P18: 1 | S18: =COUNT(F18:R18) -> 2
A19: hab_comunicacion | B19: Comunicación | C19: Explico las cosas claro y converso con la gente | D19: Habilidad | E19: =INDEX(Supuestos!$B$5:$B$8,MATCH(D19,Supuestos!$A$5:$A$8,0)) -> 2 | L19: 1 | P19: 1 | S19: =COUNT(F19:R19) -> 2
A20: hab_inventario | B20: Control de inventario | C20: Veo qué falta y llevo la cuenta | D20: Habilidad | E20: =INDEX(Supuestos!$B$5:$B$8,MATCH(D20,Supuestos!$A$5:$A$8,0)) -> 2 | H20: 1 | M20: 1 | S20: =COUNT(F20:R20) -> 2
A21: hab_cuadre_caja | B21: Cuadre de caja | C21: Cuadro la caja al final del día | D21: Habilidad | E21: =INDEX(Supuestos!$B$5:$B$8,MATCH(D21,Supuestos!$A$5:$A$8,0)) -> 2 | F21: 1 | S21: =COUNT(F21:R21) -> 1
A22: hab_cuidado_personas | B22: Cuidado de personas | C22: Cuido a niños o adultos mayores | D22: Habilidad | E22: =INDEX(Supuestos!$B$5:$B$8,MATCH(D22,Supuestos!$A$5:$A$8,0)) -> 2 | Q22: 1 | S22: =COUNT(F22:R22) -> 1
A23: hab_identifica_necesidades | B23: Detectar necesidades | C23: Me doy cuenta de lo que la gente necesita | D23: Habilidad | E23: =INDEX(Supuestos!$B$5:$B$8,MATCH(D23,Supuestos!$A$5:$A$8,0)) -> 2 | P23: 1 | S23: =COUNT(F23:R23) -> 1
A24: hab_limpieza_tecnica | B24: Limpieza y desinfección | C24: Limpio bien cada tipo de lugar | D24: Habilidad | E24: =INDEX(Supuestos!$B$5:$B$8,MATCH(D24,Supuestos!$A$5:$A$8,0)) -> 2 | J24: 1 | K24: 1 | S24: =COUNT(F24:R24) -> 2
A25: hab_maquinas_produccion | B25: Manejo de máquinas | C25: Trabajo con máquinas o en línea de producción | D25: Habilidad | E25: =INDEX(Supuestos!$B$5:$B$8,MATCH(D25,Supuestos!$A$5:$A$8,0)) -> 2 | O25: 1 | S25: =COUNT(F25:R25) -> 1
A26: hab_mantenimiento_basico | B26: Mantenimiento básico | C26: Arreglo y pinto cosas sencillas | D26: Habilidad | E26: =INDEX(Supuestos!$B$5:$B$8,MATCH(D26,Supuestos!$A$5:$A$8,0)) -> 2 | R26: 1 | S26: =COUNT(F26:R26) -> 1
A27: hab_organizacion_tiempos | B27: Organización del tiempo | C27: Organizo mi tiempo para que todo salga a la hora | D27: Habilidad | E27: =INDEX(Supuestos!$B$5:$B$8,MATCH(D27,Supuestos!$A$5:$A$8,0)) -> 2 | K27: 1 | S27: =COUNT(F27:R27) -> 1
A28: hab_carga_descarga | B28: Recepción de mercadería | C28: Recibo y descargo mercadería | D28: Habilidad | E28: =INDEX(Supuestos!$B$5:$B$8,MATCH(D28,Supuestos!$A$5:$A$8,0)) -> 2 | H28: 1 | M28: 1 | S28: =COUNT(F28:R28) -> 2
A29: hab_registro_datos | B29: Registro de datos | C29: Anoto todo sin equivocarme | D29: Habilidad | E29: =INDEX(Supuestos!$B$5:$B$8,MATCH(D29,Supuestos!$A$5:$A$8,0)) -> 2 | I29: 1 | M29: 1 | P29: 1 | R29: 1 | S29: =COUNT(F29:R29) -> 4
A30: hab_reparto_rutas | B30: Reparto y rutas | C30: Reparto pedidos y conozco las rutas | D30: Habilidad | E30: =INDEX(Supuestos!$B$5:$B$8,MATCH(D30,Supuestos!$A$5:$A$8,0)) -> 2 | N30: 1 | S30: =COUNT(F30:R30) -> 1
A31: hab_reposicion | B31: Reposición | C31: Repongo y ordeno lo que falta | D31: Habilidad | E31: =INDEX(Supuestos!$B$5:$B$8,MATCH(D31,Supuestos!$A$5:$A$8,0)) -> 2 | G31: 1 | H31: 1 | S31: =COUNT(F31:R31) -> 2
A32: hab_servicio_mesa | B32: Servicio de mesa | C32: Atiendo mesas y tomo pedidos | D32: Habilidad | E32: =INDEX(Supuestos!$B$5:$B$8,MATCH(D32,Supuestos!$A$5:$A$8,0)) -> 2 | L32: 1 | S32: =COUNT(F32:R32) -> 1
A33: hab_tecnicas_venta | B33: Técnicas de venta | C33: Sé ofrecer y convencer para vender | D33: Habilidad | E33: =INDEX(Supuestos!$B$5:$B$8,MATCH(D33,Supuestos!$A$5:$A$8,0)) -> 2 | G33: 1 | S33: =COUNT(F33:R33) -> 1
A34: cua_cumple_protocolos | B34: Cumplimiento de normas | C34: Sigo las normas y los pasos al pie de la letra | D34: Cualidad | E34: =INDEX(Supuestos!$B$5:$B$8,MATCH(D34,Supuestos!$A$5:$A$8,0)) -> 1 | O34: 1 | R34: 1 | S34: =COUNT(F34:R34) -> 2
A35: cua_honestidad | B35: Honestidad | C35: Me confían cosas importantes | D35: Cualidad | E35: =INDEX(Supuestos!$B$5:$B$8,MATCH(D35,Supuestos!$A$5:$A$8,0)) -> 1 | F35: 1 | J35: 1 | N35: 1 | Q35: 1 | R35: 1 | S35: =COUNT(F35:R35) -> 5
A36: cua_orden | B36: Organización y orden | C36: Soy ordenada y me fijo en los detalles | D36: Cualidad | E36: =INDEX(Supuestos!$B$5:$B$8,MATCH(D36,Supuestos!$A$5:$A$8,0)) -> 1 | H36: 1 | I36: 1 | M36: 1 | O36: 1 | S36: =COUNT(F36:R36) -> 4
A37: cua_paciencia | B37: Paciencia | C37: Tengo paciencia con la gente | D37: Cualidad | E37: =INDEX(Supuestos!$B$5:$B$8,MATCH(D37,Supuestos!$A$5:$A$8,0)) -> 1 | F37: 1 | G37: 1 | L37: 1 | P37: 1 | Q37: 1 | S37: =COUNT(F37:R37) -> 5
A38: cua_puntualidad | B38: Puntualidad | C38: Soy puntual y cumplo | D38: Cualidad | E38: =INDEX(Supuestos!$B$5:$B$8,MATCH(D38,Supuestos!$A$5:$A$8,0)) -> 1 | I38: 1 | J38: 1 | N38: 1 | Q38: 1 | R38: 1 | S38: =COUNT(F38:R38) -> 5
A39: cua_resistencia | B39: Resistencia física | C39: Aguanto el ritmo todo el día | D39: Cualidad | E39: =INDEX(Supuestos!$B$5:$B$8,MATCH(D39,Supuestos!$A$5:$A$8,0)) -> 1 | H39: 1 | J39: 1 | M39: 1 | N39: 1 | O39: 1 | S39: =COUNT(F39:R39) -> 5
A40: cua_trabajo_presion | B40: Trabajo bajo presión | C40: Trabajo tranquila aunque haya mucha gente o apuro | D40: Cualidad | E40: =INDEX(Supuestos!$B$5:$B$8,MATCH(D40,Supuestos!$A$5:$A$8,0)) -> 1 | K40: 1 | L40: 1 | S40: =COUNT(F40:R40) -> 2
A41: cua_trabajo_equipo | B41: Trabajo en equipo | C41: Ayudo a mis compañeros | D41: Cualidad | E41: =INDEX(Supuestos!$B$5:$B$8,MATCH(D41,Supuestos!$A$5:$A$8,0)) -> 1 | K41: 1 | O41: 1 | S41: =COUNT(F41:R41) -> 2
A42: comp_ambientes_impecables | B42: Ambientes impecables | C42: Dejo todo limpio a tiempo | D42: Logro (competencia) | E42: =INDEX(Supuestos!$B$5:$B$8,MATCH(D42,Supuestos!$A$5:$A$8,0)) -> 3 | J42: 1 | R42: 1 | S42: =COUNT(F42:R42) -> 2
A43: comp_caja_sin_faltantes | B43: Caja sin faltantes | C43: Mi caja siempre cuadra | D43: Logro (competencia) | E43: =INDEX(Supuestos!$B$5:$B$8,MATCH(D43,Supuestos!$A$5:$A$8,0)) -> 3 | F43: 1 | S43: =COUNT(F43:R43) -> 1
A44: comp_clientes_vuelven | B44: Clientes que vuelven | C44: Mis clientes vuelven y me recomiendan | D44: Logro (competencia) | E44: =INDEX(Supuestos!$B$5:$B$8,MATCH(D44,Supuestos!$A$5:$A$8,0)) -> 3 | L44: 1 | Q44: 1 | S44: =COUNT(F44:R44) -> 2
A45: comp_gestiona_documentos | B45: Documentos al día | C45: Tengo todo al día | D45: Logro (competencia) | E45: =INDEX(Supuestos!$B$5:$B$8,MATCH(D45,Supuestos!$A$5:$A$8,0)) -> 3 | I45: 1 | S45: =COUNT(F45:R45) -> 1
A46: comp_meta_turno | B46: Meta del turno | C46: Cumplo la meta de mi turno | D46: Logro (competencia) | E46: =INDEX(Supuestos!$B$5:$B$8,MATCH(D46,Supuestos!$A$5:$A$8,0)) -> 3 | O46: 1 | S46: =COUNT(F46:R46) -> 1
A47: comp_pedidos_a_tiempo | B47: Pedidos a tiempo | C47: Mis pedidos salen completos y a tiempo | D47: Logro (competencia) | E47: =INDEX(Supuestos!$B$5:$B$8,MATCH(D47,Supuestos!$A$5:$A$8,0)) -> 3 | K47: 1 | M47: 1 | N47: 1 | S47: =COUNT(F47:R47) -> 3
A48: comp_resuelve_reclamos | B48: Resolver reclamos | C48: Calmo al cliente molesto y lo resuelvo | D48: Logro (competencia) | E48: =INDEX(Supuestos!$B$5:$B$8,MATCH(D48,Supuestos!$A$5:$A$8,0)) -> 3 | G48: 1 | P48: 1 | S48: =COUNT(F48:R48) -> 2
A49: comp_gondola_abastecida | B49: Zona siempre abastecida | C49: Nunca falta producto en mi zona | D49: Logro (competencia) | E49: =INDEX(Supuestos!$B$5:$B$8,MATCH(D49,Supuestos!$A$5:$A$8,0)) -> 3 | H49: 1 | S49: =COUNT(F49:R49) -> 1
B50: Habilidades que pide | F50: =COUNT(F6:F49) -> 7 | G50: =COUNT(G6:G49) -> 7 | H50: =COUNT(H6:H49) -> 7 | I50: =COUNT(I6:I49) -> 7 | J50: =COUNT(J6:J49) -> 7 | K50: =COUNT(K6:K49) -> 7 | L50: =COUNT(L6:L49) -> 7 | M50: =COUNT(M6:M49) -> 7 | ... R50: =COUNT(R6:R49) -> 7
B51: Suma de pesos que pide (denominador) | F51: =SUMPRODUCT($E$6:$E$49,F6:F49) -> 13 | G51: =SUMPRODUCT($E$6:$E$49,G6:G49) -> 14 | H51: =SUMPRODUCT($E$6:$E$49,H6:H49) -> 13 | I51: =SUMPRODUCT($E$6:$E$49,I6:I49) -> 13 | J51: =SUMPRODUCT($E$6:$E$49,J6:J49) -> 12 | K51: =SUMPRODUCT($E$6:$E$49,K6:K49) -> 13 | L51: =SUMPRODUCT($E$6:$E$49,L6:L49) -> 13 | M51: =SUMPRODUCT($E$6:$E$49,M6:M49) -> 13 | ... R51: =SUMPRODUCT($E$6:$E$49,R6:R49) -> 12
A53: Se muestran las 44 habilidades del catálogo que pide al menos una ocupación (el catálogo tiene 48).

Sheet Proximidad
A1: Matriz de proximidad entre ocupaciones
A2: Fila = oficio de hoy (lo que la persona ya sabe). Columna = ocupación a la que podría pasar. Valor = % ponderado de lo que pide la columna que ya tiene la fila.
B5: Oficio de hoy ↓ / Podría pasar a → | C5: Cajero/a | D5: Vendedor/a de tienda | E5: Reponedor/a y abastecedor/a | F5: Auxiliar administrativo/a | G5: Personal de limpieza | H5: Ayudante de cocina | I5: Mozo/a de restaurante | J5: Auxiliar de almacén | K5: Repartidor/a | L5: Operario/a de producción | M5: Asesor/a de atención al cliente | N5: Cuidador/a de personas | O5: Conserje / mantenimiento
B6: Cajero/a | C6: — | D6: =SUMPRODUCT('Matriz habilidades'!$E$6:$E$49,'Matriz habilidades'!$F$6:$F$49,'Matriz habilidades'!$G$6:$G$49)/SUMPRODUCT('Matriz habilidades'!$E$6:$E$49,'Matriz habilidades'!$G$6:$G$49) -> 0.5 | E6: =SUMPRODUCT('Matriz habilidades'!$E$6:$E$49,'Matriz habilidades'!$F$6:$F$49,'Matriz habilidades'!$H$6:$H$49)/SUMPRODUCT('Matriz habilidades'!$E$6:$E$49,'Matriz habilidades'!$H$6:$H$49) -> 0 | F6: =SUMPRODUCT('Matriz habilidades'!$E$6:$E$49,'Matriz habilidades'!$F$6:$F$49,'Matriz habilidades'!$I$6:$I$49)/SUMPRODUCT('Matriz habilidades'!$E$6:$E$49,'Matriz habilidades'!$I$6:$I$49) -> 0 | G6: =SUMPRODUCT('Matriz habilidades'!$E$6:$E$49,'Matriz habilidades'!$F$6:$F$49,'Matriz habilidades'!$J$6:$J$49)/SUMPRODUCT('Matriz habilidades'!$E$6:$E$49,'Matriz habilidades'!$J$6:$J$49) -> 0.083333333 | H6: =SUMPRODUCT('Matriz habilidades'!$E$6:$E$49,'Matriz habilidades'!$F$6:$F$49,'Matriz habilidades'!$K$6:$K$49)/SUMPRODUCT('Matriz habilidades'!$E$6:$E$49,'Matriz habilidades'!$K$6:$K$49) -> 0 | I6: =SUMPRODUCT('Matriz habilidades'!$E$6:$E$49,'Matriz habilidades'!$F$6:$F$49,'Matriz habilidades'!$L$6:$L$49)/SUMPRODUCT('Matriz habilidades'!$E$6:$E$49,'Matriz habilidades'!$L$6:$L$49) -> 0.38461538 | J6: =SUMPRODUCT('Matriz habilidades'!$E$6:$E$49,'Matriz habilidades'!$F$6:$F$49,'Matriz habilidades'!$M$6:$M$49)/SUMPRODUCT('Matriz habilidades'!$E$6:$E$49,'Matriz habilidades'!$M$6:$M$49) -> 0 | K6: =SUMPRODUCT('Matriz habilidades'!$E$6:$E$49,'Matriz habilidades'!$F$6:$F$49,'Matriz habilidades'!$N$6:$N$49)/SUMPRODUCT('Matriz habilidades'!$E$6:$E$49,'Matriz habilidades'!$N$6:$N$49) -> 0.25 | L6: =SUMPRODUCT('Matriz habilidades'!$E$6:$E$49,'Matriz habilidades'!$F$6:$F$49,'Matriz habilidades'!$O$6:$O$49)/SUMPRODUCT('Matriz habilidades'!$E$6:$E$49,'Matriz habilidades'!$O$6:$O$49) -> 0 | M6: =SUMPRODUCT('Matriz habilidades'!$E$6:$E$49,'Matriz habilidades'!$F$6:$F$49,'Matriz habilidades'!$P$6:$P$49)/SUMPRODUCT('Matriz habilidades'!$E$6:$E$49,'Matriz habilidades'!$P$6:$P$49) -> 0.071428571 | N6: =SUMPRODUCT('Matriz habilidades'!$E$6:$E$49,'Matriz habilidades'!$F$6:$F$49,'Matriz habilidades'!$Q$6:$Q$49)/SUMPRODUCT('Matriz habilidades'!$E$6:$E$49,'Matriz habilidades'!$Q$6:$Q$49) -> 0.16666667 | O6: =SUMPRODUCT('Matriz habilidades'!$E$6:$E$49,'Matriz habilidades'!$F$6:$F$49,'Matriz habilidades'!$R$6:$R$49)/SUMPRODUCT('Matriz habilidades'!$E$6:$E$49,'Matriz habilidades'!$R$6:$R$49) -> 0.083333333
B7: Vendedor/a de tienda | C7: =SUMPRODUCT('Matriz habilidades'!$E$6:$E$49,'Matriz habilidades'!$G$6:$G$49,'Matriz habilidades'!$F$6:$F$49)/SUMPRODUCT('Matriz habilidades'!$E$6:$E$49,'Matriz habilidades'!$F$6:$F$49) -> 0.53846154 | D7: — | E7: =SUMPRODUCT('Matriz habilidades'!$E$6:$E$49,'Matriz habilidades'!$G$6:$G$49,'Matriz habilidades'!$H$6:$H$49)/SUMPRODUCT('Matriz habilidades'!$E$6:$E$49,'Matriz habilidades'!$H$6:$H$49) -> 0.15384615 | F7: =SUMPRODUCT('Matriz habilidades'!$E$6:$E$49,'Matriz habilidades'!$G$6:$G$49,'Matriz habilidades'!$I$6:$I$49)/SUMPRODUCT('Matriz habilidades'!$E$6:$E$49,'Matriz habilidades'!$I$6:$I$49) -> 0 | G7: =SUMPRODUCT('Matriz habilidades'!$E$6:$E$49,'Matriz habilidades'!$G$6:$G$49,'Matriz habilidades'!$J$6:$J$49)/SUMPRODUCT('Matriz habilidades'!$E$6:$E$49,'Matriz habilidades'!$J$6:$J$49) -> 0 | H7: =SUMPRODUCT('Matriz habilidades'!$E$6:$E$49,'Matriz habilidades'!$G$6:$G$49,'Matriz habilidades'!$K$6:$K$49)/SUMPRODUCT('Matriz habilidades'!$E$6:$E$49,'Matriz habilidades'!$K$6:$K$49) -> 0 | I7: =SUMPRODUCT('Matriz habilidades'!$E$6:$E$49,'Matriz habilidades'!$G$6:$G$49,'Matriz habilidades'!$L$6:$L$49)/SUMPRODUCT('Matriz habilidades'!$E$6:$E$49,'Matriz habilidades'!$L$6:$L$49) -> 0.38461538 | J7: =SUMPRODUCT('Matriz habilidades'!$E$6:$E$49,'Matriz habilidades'!$G$6:$G$49,'Matriz habilidades'!$M$6:$M$49)/SUMPRODUCT('Matriz habilidades'!$E$6:$E$49,'Matriz habilidades'!$M$6:$M$49) -> 0 | K7: =SUMPRODUCT('Matriz habilidades'!$E$6:$E$49,'Matriz habilidades'!$G$6:$G$49,'Matriz habilidades'!$N$6:$N$49)/SUMPRODUCT('Matriz habilidades'!$E$6:$E$49,'Matriz habilidades'!$N$6:$N$49) -> 0.16666667 | L7: =SUMPRODUCT('Matriz habilidades'!$E$6:$E$49,'Matriz habilidades'!$G$6:$G$49,'Matriz habilidades'!$O$6:$O$49)/SUMPRODUCT('Matriz habilidades'!$E$6:$E$49,'Matriz habilidades'!$O$6:$O$49) -> 0 | M7: =SUMPRODUCT('Matriz habilidades'!$E$6:$E$49,'Matriz habilidades'!$G$6:$G$49,'Matriz habilidades'!$P$6:$P$49)/SUMPRODUCT('Matriz habilidades'!$E$6:$E$49,'Matriz habilidades'!$P$6:$P$49) -> 0.28571429 | N7: =SUMPRODUCT('Matriz habilidades'!$E$6:$E$49,'Matriz habilidades'!$G$6:$G$49,'Matriz habilidades'!$Q$6:$Q$49)/SUMPRODUCT('Matriz habilidades'!$E$6:$E$49,'Matriz habilidades'!$Q$6:$Q$49) -> 0.083333333 | O7: =SUMPRODUCT('Matriz habilidades'!$E$6:$E$49,'Matriz habilidades'!$G$6:$G$49,'Matriz habilidades'!$R$6:$R$49)/SUMPRODUCT('Matriz habilidades'!$E$6:$E$49,'Matriz habilidades'!$R$6:$R$49) -> 0
B8: Reponedor/a y abastecedor/a | C8: =SUMPRODUCT('Matriz habilidades'!$E$6:$E$49,'Matriz habilidades'!$H$6:$H$49,'Matriz habilidades'!$F$6:$F$49)/SUMPRODUCT('Matriz habilidades'!$E$6:$E$49,'Matriz habilidades'!$F$6:$F$49) -> 0 | D8: =SUMPRODUCT('Matriz habilidades'!$E$6:$E$49,'Matriz habilidades'!$H$6:$H$49,'Matriz habilidades'!$G$6:$G$49)/SUMPRODUCT('Matriz habilidades'!$E$6:$E$49,'Matriz habilidades'!$G$6:$G$49) -> 0.14285714 | E8: — | F8: =SUMPRODUCT('Matriz habilidades'!$E$6:$E$49,'Matriz habilidades'!$H$6:$H$49,'Matriz habilidades'!$I$6:$I$49)/SUMPRODUCT('Matriz habilidades'!$E$6:$E$49,'Matriz habilidades'!$I$6:$I$49) -> 0.076923077 | G8: =SUMPRODUCT('Matriz habilidades'!$E$6:$E$49,'Matriz habilidades'!$H$6:$H$49,'Matriz habilidades'!$J$6:$J$49)/SUMPRODUCT('Matriz habilidades'!$E$6:$E$49,'Matriz habilidades'!$J$6:$J$49) -> 0.083333333 | H8: =SUMPRODUCT('Matriz habilidades'!$E$6:$E$49,'Matriz habilidades'!$H$6:$H$49,'Matriz habilidades'!$K$6:$K$49)/SUMPRODUCT('Matriz habilidades'!$E$6:$E$49,'Matriz habilidades'!$K$6:$K$49) -> 0 | I8: =SUMPRODUCT('Matriz habilidades'!$E$6:$E$49,'Matriz habilidades'!$H$6:$H$49,'Matriz habilidades'!$L$6:$L$49)/SUMPRODUCT('Matriz habilidades'!$E$6:$E$49,'Matriz habilidades'!$L$6:$L$49) -> 0 | J8: =SUMPRODUCT('Matriz habilidades'!$E$6:$E$49,'Matriz habilidades'!$H$6:$H$49,'Matriz habilidades'!$M$6:$M$49)/SUMPRODUCT('Matriz habilidades'!$E$6:$E$49,'Matriz habilidades'!$M$6:$M$49) -> 0.46153846 | K8: =SUMPRODUCT('Matriz habilidades'!$E$6:$E$49,'Matriz habilidades'!$H$6:$H$49,'Matriz habilidades'!$N$6:$N$49)/SUMPRODUCT('Matriz habilidades'!$E$6:$E$49,'Matriz habilidades'!$N$6:$N$49) -> 0.083333333 | L8: =SUMPRODUCT('Matriz habilidades'!$E$6:$E$49,'Matriz habilidades'!$H$6:$H$49,'Matriz habilidades'!$O$6:$O$49)/SUMPRODUCT('Matriz habilidades'!$E$6:$E$49,'Matriz habilidades'!$O$6:$O$49) -> 0.18181818 | M8: =SUMPRODUCT('Matriz habilidades'!$E$6:$E$49,'Matriz habilidades'!$H$6:$H$49,'Matriz habilidades'!$P$6:$P$49)/SUMPRODUCT('Matriz habilidades'!$E$6:$E$49,'Matriz habilidades'!$P$6:$P$49) -> 0 | N8: =SUMPRODUCT('Matriz habilidades'!$E$6:$E$49,'Matriz habilidades'!$H$6:$H$49,'Matriz habilidades'!$Q$6:$Q$49)/SUMPRODUCT('Matriz habilidades'!$E$6:$E$49,'Matriz habilidades'!$Q$6:$Q$49) -> 0 | O8: =SUMPRODUCT('Matriz habilidades'!$E$6:$E$49,'Matriz habilidades'!$H$6:$H$49,'Matriz habilidades'!$R$6:$R$49)/SUMPRODUCT('Matriz habilidades'!$E$6:$E$49,'Matriz habilidades'!$R$6:$R$49) -> 0
B9: Auxiliar administrativo/a | C9: =SUMPRODUCT('Matriz habilidades'!$E$6:$E$49,'Matriz habilidades'!$I$6:$I$49,'Matriz habilidades'!$F$6:$F$49)/SUMPRODUCT('Matriz habilidades'!$E$6:$E$49,'Matriz habilidades'!$F$6:$F$49) -> 0 | D9: =SUMPRODUCT('Matriz habilidades'!$E$6:$E$49,'Matriz habilidades'!$I$6:$I$49,'Matriz habilidades'!$G$6:$G$49)/SUMPRODUCT('Matriz habilidades'!$E$6:$E$49,'Matriz habilidades'!$G$6:$G$49) -> 0 | E9: =SUMPRODUCT('Matriz habilidades'!$E$6:$E$49,'Matriz habilidades'!$I$6:$I$49,'Matriz habilidades'!$H$6:$H$49)/SUMPRODUCT('Matriz habilidades'!$E$6:$E$49,'Matriz habilidades'!$H$6:$H$49) -> 0.076923077 | F9: — | G9: =SUMPRODUCT('Matriz habilidades'!$E$6:$E$49,'Matriz habilidades'!$I$6:$I$49,'Matriz habilidades'!$J$6:$J$49)/SUMPRODUCT('Matriz habilidades'!$E$6:$E$49,'Matriz habilidades'!$J$6:$J$49) -> 0.083333333 | H9: =SUMPRODUCT('Matriz habilidades'!$E$6:$E$49,'Matriz habilidades'!$I$6:$I$49,'Matriz habilidades'!$K$6:$K$49)/SUMPRODUCT('Matriz habilidades'!$E$6:$E$49,'Matriz habilidades'!$K$6:$K$49) -> 0 | I9: =SUMPRODUCT('Matriz habilidades'!$E$6:$E$49,'Matriz habilidades'!$I$6:$I$49,'Matriz habilidades'!$L$6:$L$49)/SUMPRODUCT('Matriz habilidades'!$E$6:$E$49,'Matriz habilidades'!$L$6:$L$49) -> 0 | J9: =SUMPRODUCT('Matriz habilidades'!$E$6:$E$49,'Matriz habilidades'!$I$6:$I$49,'Matriz habilidades'!$M$6:$M$49)/SUMPRODUCT('Matriz habilidades'!$E$6:$E$49,'Matriz habilidades'!$M$6:$M$49) -> 0.23076923 | K9: =SUMPRODUCT('Matriz habilidades'!$E$6:$E$49,'Matriz habilidades'!$I$6:$I$49,'Matriz habilidades'!$N$6:$N$49)/SUMPRODUCT('Matriz habilidades'!$E$6:$E$49,'Matriz habilidades'!$N$6:$N$49) -> 0.083333333 | L9: =SUMPRODUCT('Matriz habilidades'!$E$6:$E$49,'Matriz habilidades'!$I$6:$I$49,'Matriz habilidades'!$O$6:$O$49)/SUMPRODUCT('Matriz habilidades'!$E$6:$E$49,'Matriz habilidades'!$O$6:$O$49) -> 0.090909091 | M9: =SUMPRODUCT('Matriz habilidades'!$E$6:$E$49,'Matriz habilidades'!$I$6:$I$49,'Matriz habilidades'!$P$6:$P$49)/SUMPRODUCT('Matriz habilidades'!$E$6:$E$49,'Matriz habilidades'!$P$6:$P$49) -> 0.28571429 | N9: =SUMPRODUCT('Matriz habilidades'!$E$6:$E$49,'Matriz habilidades'!$I$6:$I$49,'Matriz habilidades'!$Q$6:$Q$49)/SUMPRODUCT('Matriz habilidades'!$E$6:$E$49,'Matriz habilidades'!$Q$6:$Q$49) -> 0.083333333 | O9: =SUMPRODUCT('Matriz habilidades'!$E$6:$E$49,'Matriz habilidades'!$I$6:$I$49,'Matriz habilidades'!$R$6:$R$49)/SUMPRODUCT('Matriz habilidades'!$E$6:$E$49,'Matriz habilidades'!$R$6:$R$49) -> 0.25
B10: Personal de limpieza | C10: =SUMPRODUCT('Matriz habilidades'!$E$6:$E$49,'Matriz habilidades'!$J$6:$J$49,'Matriz habilidades'!$F$6:$F$49)/SUMPRODUCT('Matriz habilidades'!$E$6:$E$49,'Matriz habilidades'!$F$6:$F$49) -> 0.076923077 | D10: =SUMPRODUCT('Matriz habilidades'!$E$6:$E$49,'Matriz habilidades'!$J$6:$J$49,'Matriz habilidades'!$G$6:$G$49)/SUMPRODUCT('Matriz habilidades'!$E$6:$E$49,'Matriz habilidades'!$G$6:$G$49) -> 0 | E10: =SUMPRODUCT('Matriz habilidades'!$E$6:$E$49,'Matriz habilidades'!$J$6:$J$49,'Matriz habilidades'!$H$6:$H$49)/SUMPRODUCT('Matriz habilidades'!$E$6:$E$49,'Matriz habilidades'!$H$6:$H$49) -> 0.076923077 | F10: =SUMPRODUCT('Matriz habilidades'!$E$6:$E$49,'Matriz habilidades'!$J$6:$J$49,'Matriz habilidades'!$I$6:$I$49)/SUMPRODUCT('Matriz habilidades'!$E$6:$E$49,'Matriz habilidades'!$I$6:$I$49) -> 0.076923077 | G10: — | H10: =SUMPRODUCT('Matriz habilidades'!$E$6:$E$49,'Matriz habilidades'!$J$6:$J$49,'Matriz habilidades'!$K$6:$K$49)/SUMPRODUCT('Matriz habilidades'!$E$6:$E$49,'Matriz habilidades'!$K$6:$K$49) -> 0.15384615 | I10: =SUMPRODUCT('Matriz habilidades'!$E$6:$E$49,'Matriz habilidades'!$J$6:$J$49,'Matriz habilidades'!$L$6:$L$49)/SUMPRODUCT('Matriz habilidades'!$E$6:$E$49,'Matriz habilidades'!$L$6:$L$49) -> 0 | J10: =SUMPRODUCT('Matriz habilidades'!$E$6:$E$49,'Matriz habilidades'!$J$6:$J$49,'Matriz habilidades'!$M$6:$M$49)/SUMPRODUCT('Matriz habilidades'!$E$6:$E$49,'Matriz habilidades'!$M$6:$M$49) -> 0.23076923 | K10: =SUMPRODUCT('Matriz habilidades'!$E$6:$E$49,'Matriz habilidades'!$J$6:$J$49,'Matriz habilidades'!$N$6:$N$49)/SUMPRODUCT('Matriz habilidades'!$E$6:$E$49,'Matriz habilidades'!$N$6:$N$49) -> 0.25 | L10: =SUMPRODUCT('Matriz habilidades'!$E$6:$E$49,'Matriz habilidades'!$J$6:$J$49,'Matriz habilidades'!$O$6:$O$49)/SUMPRODUCT('Matriz habilidades'!$E$6:$E$49,'Matriz habilidades'!$O$6:$O$49) -> 0.27272727 | M10: =SUMPRODUCT('Matriz habilidades'!$E$6:$E$49,'Matriz habilidades'!$J$6:$J$49,'Matriz habilidades'!$P$6:$P$49)/SUMPRODUCT('Matriz habilidades'!$E$6:$E$49,'Matriz habilidades'!$P$6:$P$49) -> 0 | N10: =SUMPRODUCT('Matriz habilidades'!$E$6:$E$49,'Matriz habilidades'!$J$6:$J$49,'Matriz habilidades'!$Q$6:$Q$49)/SUMPRODUCT('Matriz habilidades'!$E$6:$E$49,'Matriz habilidades'!$Q$6:$Q$49) -> 0.16666667 | O10: =SUMPRODUCT('Matriz habilidades'!$E$6:$E$49,'Matriz habilidades'!$J$6:$J$49,'Matriz habilidades'!$R$6:$R$49)/SUMPRODUCT('Matriz habilidades'!$E$6:$E$49,'Matriz habilidades'!$R$6:$R$49) -> 0.58333333
B11: Ayudante de cocina | C11: =SUMPRODUCT('Matriz habilidades'!$E$6:$E$49,'Matriz habilidades'!$K$6:$K$49,'Matriz habilidades'!$F$6:$F$49)/SUMPRODUCT('Matriz habilidades'!$E$6:$E$49,'Matriz habilidades'!$F$6:$F$49) -> 0 | D11: =SUMPRODUCT('Matriz habilidades'!$E$6:$E$49,'Matriz habilidades'!$K$6:$K$49,'Matriz habilidades'!$G$6:$G$49)/SUMPRODUCT('Matriz habilidades'!$E$6:$E$49,'Matriz habilidades'!$G$6:$G$49) -> 0 | E11: =SUMPRODUCT('Matriz habilidades'!$E$6:$E$49,'Matriz habilidades'!$K$6:$K$49,'Matriz habilidades'!$H$6:$H$49)/SUMPRODUCT('Matriz habilidades'!$E$6:$E$49,'Matriz habilidades'!$H$6:$H$49) -> 0 | F11: =SUMPRODUCT('Matriz habilidades'!$E$6:$E$49,'Matriz habilidades'!$K$6:$K$49,'Matriz habilidades'!$I$6:$I$49)/SUMPRODUCT('Matriz habilidades'!$E$6:$E$49,'Matriz habilidades'!$I$6:$I$49) -> 0 | G11: =SUMPRODUCT('Matriz habilidades'!$E$6:$E$49,'Matriz habilidades'!$K$6:$K$49,'Matriz habilidades'!$J$6:$J$49)/SUMPRODUCT('Matriz habilidades'!$E$6:$E$49,'Matriz habilidades'!$J$6:$J$49) -> 0.16666667 | H11: — | I11: =SUMPRODUCT('Matriz habilidades'!$E$6:$E$49,'Matriz habilidades'!$K$6:$K$49,'Matriz habilidades'!$L$6:$L$49)/SUMPRODUCT('Matriz habilidades'!$E$6:$E$49,'Matriz habilidades'!$L$6:$L$49) -> 0.076923077 | J11: =SUMPRODUCT('Matriz habilidades'!$E$6:$E$49,'Matriz habilidades'!$K$6:$K$49,'Matriz habilidades'!$M$6:$M$49)/SUMPRODUCT('Matriz habilidades'!$E$6:$E$49,'Matriz habilidades'!$M$6:$M$49) -> 0.23076923 | K11: =SUMPRODUCT('Matriz habilidades'!$E$6:$E$49,'Matriz habilidades'!$K$6:$K$49,'Matriz habilidades'!$N$6:$N$49)/SUMPRODUCT('Matriz habilidades'!$E$6:$E$49,'Matriz habilidades'!$N$6:$N$49) -> 0.25 | L11: =SUMPRODUCT('Matriz habilidades'!$E$6:$E$49,'Matriz habilidades'!$K$6:$K$49,'Matriz habilidades'!$O$6:$O$49)/SUMPRODUCT('Matriz habilidades'!$E$6:$E$49,'Matriz habilidades'!$O$6:$O$49) -> 0.090909091 | M11: =SUMPRODUCT('Matriz habilidades'!$E$6:$E$49,'Matriz habilidades'!$K$6:$K$49,'Matriz habilidades'!$P$6:$P$49)/SUMPRODUCT('Matriz habilidades'!$E$6:$E$49,'Matriz habilidades'!$P$6:$P$49) -> 0 | N11: =SUMPRODUCT('Matriz habilidades'!$E$6:$E$49,'Matriz habilidades'!$K$6:$K$49,'Matriz habilidades'!$Q$6:$Q$49)/SUMPRODUCT('Matriz habilidades'!$E$6:$E$49,'Matriz habilidades'!$Q$6:$Q$49) -> 0.33333333 | O11: =SUMPRODUCT('Matriz habilidades'!$E$6:$E$49,'Matriz habilidades'!$K$6:$K$49,'Matriz habilidades'!$R$6:$R$49)/SUMPRODUCT('Matriz habilidades'!$E$6:$E$49,'Matriz habilidades'!$R$6:$R$49) -> 0
B12: Mozo/a de restaurante | C12: =SUMPRODUCT('Matriz habilidades'!$E$6:$E$49,'Matriz habilidades'!$L$6:$L$49,'Matriz habilidades'!$F$6:$F$49)/SUMPRODUCT('Matriz habilidades'!$E$6:$E$49,'Matriz habilidades'!$F$6:$F$49) -> 0.38461538 | D12: =SUMPRODUCT('Matriz habilidades'!$E$6:$E$49,'Matriz habilidades'!$L$6:$L$49,'Matriz habilidades'!$G$6:$G$49)/SUMPRODUCT('Matriz habilidades'!$E$6:$E$49,'Matriz habilidades'!$G$6:$G$49) -> 0.35714286 | E12: =SUMPRODUCT('Matriz habilidades'!$E$6:$E$49,'Matriz habilidades'!$L$6:$L$49,'Matriz habilidades'!$H$6:$H$49)/SUMPRODUCT('Matriz habilidades'!$E$6:$E$49,'Matriz habilidades'!$H$6:$H$49) -> 0 | F12: =SUMPRODUCT('Matriz habilidades'!$E$6:$E$49,'Matriz habilidades'!$L$6:$L$49,'Matriz habilidades'!$I$6:$I$49)/SUMPRODUCT('Matriz habilidades'!$E$6:$E$49,'Matriz habilidades'!$I$6:$I$49) -> 0 | G12: =SUMPRODUCT('Matriz habilidades'!$E$6:$E$49,'Matriz habilidades'!$L$6:$L$49,'Matriz habilidades'!$J$6:$J$49)/SUMPRODUCT('Matriz habilidades'!$E$6:$E$49,'Matriz habilidades'!$J$6:$J$49) -> 0 | H12: =SUMPRODUCT('Matriz habilidades'!$E$6:$E$49,'Matriz habilidades'!$L$6:$L$49,'Matriz habilidades'!$K$6:$K$49)/SUMPRODUCT('Matriz habilidades'!$E$6:$E$49,'Matriz habilidades'!$K$6:$K$49) -> 0.076923077 | I12: — | J12: =SUMPRODUCT('Matriz habilidades'!$E$6:$E$49,'Matriz habilidades'!$L$6:$L$49,'Matriz habilidades'!$M$6:$M$49)/SUMPRODUCT('Matriz habilidades'!$E$6:$E$49,'Matriz habilidades'!$M$6:$M$49) -> 0 | K12: =SUMPRODUCT('Matriz habilidades'!$E$6:$E$49,'Matriz habilidades'!$L$6:$L$49,'Matriz habilidades'!$N$6:$N$49)/SUMPRODUCT('Matriz habilidades'!$E$6:$E$49,'Matriz habilidades'!$N$6:$N$49) -> 0.16666667 | L12: =SUMPRODUCT('Matriz habilidades'!$E$6:$E$49,'Matriz habilidades'!$L$6:$L$49,'Matriz habilidades'!$O$6:$O$49)/SUMPRODUCT('Matriz habilidades'!$E$6:$E$49,'Matriz habilidades'!$O$6:$O$49) -> 0 | M12: =SUMPRODUCT('Matriz habilidades'!$E$6:$E$49,'Matriz habilidades'!$L$6:$L$49,'Matriz habilidades'!$P$6:$P$49)/SUMPRODUCT('Matriz habilidades'!$E$6:$E$49,'Matriz habilidades'!$P$6:$P$49) -> 0.21428571 | N12: =SUMPRODUCT('Matriz habilidades'!$E$6:$E$49,'Matriz habilidades'!$L$6:$L$49,'Matriz habilidades'!$Q$6:$Q$49)/SUMPRODUCT('Matriz habilidades'!$E$6:$E$49,'Matriz habilidades'!$Q$6:$Q$49) -> 0.33333333 | O12: =SUMPRODUCT('Matriz habilidades'!$E$6:$E$49,'Matriz habilidades'!$L$6:$L$49,'Matriz habilidades'!$R$6:$R$49)/SUMPRODUCT('Matriz habilidades'!$E$6:$E$49,'Matriz habilidades'!$R$6:$R$49) -> 0
B13: Auxiliar de almacén | C13: =SUMPRODUCT('Matriz habilidades'!$E$6:$E$49,'Matriz habilidades'!$M$6:$M$49,'Matriz habilidades'!$F$6:$F$49)/SUMPRODUCT('Matriz habilidades'!$E$6:$E$49,'Matriz habilidades'!$F$6:$F$49) -> 0 | D13: =SUMPRODUCT('Matriz habilidades'!$E$6:$E$49,'Matriz habilidades'!$M$6:$M$49,'Matriz habilidades'!$G$6:$G$49)/SUMPRODUCT('Matriz habilidades'!$E$6:$E$49,'Matriz habilidades'!$G$6:$G$49) -> 0 | E13: =SUMPRODUCT('Matriz habilidades'!$E$6:$E$49,'Matriz habilidades'!$M$6:$M$49,'Matriz habilidades'!$H$6:$H$49)/SUMPRODUCT('Matriz habilidades'!$E$6:$E$49,'Matriz habilidades'!$H$6:$H$49) -> 0.46153846 | F13: =SUMPRODUCT('Matriz habilidades'!$E$6:$E$49,'Matriz habilidades'!$M$6:$M$49,'Matriz habilidades'!$I$6:$I$49)/SUMPRODUCT('Matriz habilidades'!$E$6:$E$49,'Matriz habilidades'!$I$6:$I$49) -> 0.23076923 | G13: =SUMPRODUCT('Matriz habilidades'!$E$6:$E$49,'Matriz habilidades'!$M$6:$M$49,'Matriz habilidades'!$J$6:$J$49)/SUMPRODUCT('Matriz habilidades'!$E$6:$E$49,'Matriz habilidades'!$J$6:$J$49) -> 0.25 | H13: =SUMPRODUCT('Matriz habilidades'!$E$6:$E$49,'Matriz habilidades'!$M$6:$M$49,'Matriz habilidades'!$K$6:$K$49)/SUMPRODUCT('Matriz habilidades'!$E$6:$E$49,'Matriz habilidades'!$K$6:$K$49) -> 0.23076923 | I13: =SUMPRODUCT('Matriz habilidades'!$E$6:$E$49,'Matriz habilidades'!$M$6:$M$49,'Matriz habilidades'!$L$6:$L$49)/SUMPRODUCT('Matriz habilidades'!$E$6:$E$49,'Matriz habilidades'!$L$6:$L$49) -> 0 | J13: — | K13: =SUMPRODUCT('Matriz habilidades'!$E$6:$E$49,'Matriz habilidades'!$M$6:$M$49,'Matriz habilidades'!$N$6:$N$49)/SUMPRODUCT('Matriz habilidades'!$E$6:$E$49,'Matriz habilidades'!$N$6:$N$49) -> 0.33333333 | L13: =SUMPRODUCT('Matriz habilidades'!$E$6:$E$49,'Matriz habilidades'!$M$6:$M$49,'Matriz habilidades'!$O$6:$O$49)/SUMPRODUCT('Matriz habilidades'!$E$6:$E$49,'Matriz habilidades'!$O$6:$O$49) -> 0.36363636 | M13: =SUMPRODUCT('Matriz habilidades'!$E$6:$E$49,'Matriz habilidades'!$M$6:$M$49,'Matriz habilidades'!$P$6:$P$49)/SUMPRODUCT('Matriz habilidades'!$E$6:$E$49,'Matriz habilidades'!$P$6:$P$49) -> 0.14285714 | N13: =SUMPRODUCT('Matriz habilidades'!$E$6:$E$49,'Matriz habilidades'!$M$6:$M$49,'Matriz habilidades'!$Q$6:$Q$49)/SUMPRODUCT('Matriz habilidades'!$E$6:$E$49,'Matriz habilidades'!$Q$6:$Q$49) -> 0 | O13: =SUMPRODUCT('Matriz habilidades'!$E$6:$E$49,'Matriz habilidades'!$M$6:$M$49,'Matriz habilidades'!$R$6:$R$49)/SUMPRODUCT('Matriz habilidades'!$E$6:$E$49,'Matriz habilidades'!$R$6:$R$49) -> 0.33333333
B14: Repartidor/a | C14: =SUMPRODUCT('Matriz habilidades'!$E$6:$E$49,'Matriz habilidades'!$N$6:$N$49,'Matriz habilidades'!$F$6:$F$49)/SUMPRODUCT('Matriz habilidades'!$E$6:$E$49,'Matriz habilidades'!$F$6:$F$49) -> 0.23076923 | D14: =SUMPRODUCT('Matriz habilidades'!$E$6:$E$49,'Matriz habilidades'!$N$6:$N$49,'Matriz habilidades'!$G$6:$G$49)/SUMPRODUCT('Matriz habilidades'!$E$6:$E$49,'Matriz habilidades'!$G$6:$G$49) -> 0.14285714 | E14: =SUMPRODUCT('Matriz habilidades'!$E$6:$E$49,'Matriz habilidades'!$N$6:$N$49,'Matriz habilidades'!$H$6:$H$49)/SUMPRODUCT('Matriz habilidades'!$E$6:$E$49,'Matriz habilidades'!$H$6:$H$49) -> 0.076923077 | F14: =SUMPRODUCT('Matriz habilidades'!$E$6:$E$49,'Matriz habilidades'!$N$6:$N$49,'Matriz habilidades'!$I$6:$I$49)/SUMPRODUCT('Matriz habilidades'!$E$6:$E$49,'Matriz habilidades'!$I$6:$I$49) -> 0.076923077 | G14: =SUMPRODUCT('Matriz habilidades'!$E$6:$E$49,'Matriz habilidades'!$N$6:$N$49,'Matriz habilidades'!$J$6:$J$49)/SUMPRODUCT('Matriz habilidades'!$E$6:$E$49,'Matriz habilidades'!$J$6:$J$49) -> 0.25 | H14: =SUMPRODUCT('Matriz habilidades'!$E$6:$E$49,'Matriz habilidades'!$N$6:$N$49,'Matriz habilidades'!$K$6:$K$49)/SUMPRODUCT('Matriz habilidades'!$E$6:$E$49,'Matriz habilidades'!$K$6:$K$49) -> 0.23076923 | I14: =SUMPRODUCT('Matriz habilidades'!$E$6:$E$49,'Matriz habilidades'!$N$6:$N$49,'Matriz habilidades'!$L$6:$L$49)/SUMPRODUCT('Matriz habilidades'!$E$6:$E$49,'Matriz habilidades'!$L$6:$L$49) -> 0.15384615 | J14: =SUMPRODUCT('Matriz habilidades'!$E$6:$E$49,'Matriz habilidades'!$N$6:$N$49,'Matriz habilidades'!$M$6:$M$49)/SUMPRODUCT('Matriz habilidades'!$E$6:$E$49,'Matriz habilidades'!$M$6:$M$49) -> 0.30769231 | K14: — | L14: =SUMPRODUCT('Matriz habilidades'!$E$6:$E$49,'Matriz habilidades'!$N$6:$N$49,'Matriz habilidades'!$O$6:$O$49)/SUMPRODUCT('Matriz habilidades'!$E$6:$E$49,'Matriz habilidades'!$O$6:$O$49) -> 0.090909091 | M14: =SUMPRODUCT('Matriz habilidades'!$E$6:$E$49,'Matriz habilidades'!$N$6:$N$49,'Matriz habilidades'!$P$6:$P$49)/SUMPRODUCT('Matriz habilidades'!$E$6:$E$49,'Matriz habilidades'!$P$6:$P$49) -> 0 | N14: =SUMPRODUCT('Matriz habilidades'!$E$6:$E$49,'Matriz habilidades'!$N$6:$N$49,'Matriz habilidades'!$Q$6:$Q$49)/SUMPRODUCT('Matriz habilidades'!$E$6:$E$49,'Matriz habilidades'!$Q$6:$Q$49) -> 0.16666667 | O14: =SUMPRODUCT('Matriz habilidades'!$E$6:$E$49,'Matriz habilidades'!$N$6:$N$49,'Matriz habilidades'!$R$6:$R$49)/SUMPRODUCT('Matriz habilidades'!$E$6:$E$49,'Matriz habilidades'!$R$6:$R$49) -> 0.16666667
B15: Operario/a de producción | C15: =SUMPRODUCT('Matriz habilidades'!$E$6:$E$49,'Matriz habilidades'!$O$6:$O$49,'Matriz habilidades'!$F$6:$F$49)/SUMPRODUCT('Matriz habilidades'!$E$6:$E$49,'Matriz habilidades'!$F$6:$F$49) -> 0 | D15: =SUMPRODUCT('Matriz habilidades'!$E$6:$E$49,'Matriz habilidades'!$O$6:$O$49,'Matriz habilidades'!$G$6:$G$49)/SUMPRODUCT('Matriz habilidades'!$E$6:$E$49,'Matriz habilidades'!$G$6:$G$49) -> 0 | E15: =SUMPRODUCT('Matriz habilidades'!$E$6:$E$49,'Matriz habilidades'!$O$6:$O$49,'Matriz habilidades'!$H$6:$H$49)/SUMPRODUCT('Matriz habilidades'!$E$6:$E$49,'Matriz habilidades'!$H$6:$H$49) -> 0.15384615 | F15: =SUMPRODUCT('Matriz habilidades'!$E$6:$E$49,'Matriz habilidades'!$O$6:$O$49,'Matriz habilidades'!$I$6:$I$49)/SUMPRODUCT('Matriz habilidades'!$E$6:$E$49,'Matriz habilidades'!$I$6:$I$49) -> 0.076923077 | G15: =SUMPRODUCT('Matriz habilidades'!$E$6:$E$49,'Matriz habilidades'!$O$6:$O$49,'Matriz habilidades'!$J$6:$J$49)/SUMPRODUCT('Matriz habilidades'!$E$6:$E$49,'Matriz habilidades'!$J$6:$J$49) -> 0.25 | H15: =SUMPRODUCT('Matriz habilidades'!$E$6:$E$49,'Matriz habilidades'!$O$6:$O$49,'Matriz habilidades'!$K$6:$K$49)/SUMPRODUCT('Matriz habilidades'!$E$6:$E$49,'Matriz habilidades'!$K$6:$K$49) -> 0.076923077 | I15: =SUMPRODUCT('Matriz habilidades'!$E$6:$E$49,'Matriz habilidades'!$O$6:$O$49,'Matriz habilidades'!$L$6:$L$49)/SUMPRODUCT('Matriz habilidades'!$E$6:$E$49,'Matriz habilidades'!$L$6:$L$49) -> 0 | J15: =SUMPRODUCT('Matriz habilidades'!$E$6:$E$49,'Matriz habilidades'!$O$6:$O$49,'Matriz habilidades'!$M$6:$M$49)/SUMPRODUCT('Matriz habilidades'!$E$6:$E$49,'Matriz habilidades'!$M$6:$M$49) -> 0.30769231 | K15: =SUMPRODUCT('Matriz habilidades'!$E$6:$E$49,'Matriz habilidades'!$O$6:$O$49,'Matriz habilidades'!$N$6:$N$49)/SUMPRODUCT('Matriz habilidades'!$E$6:$E$49,'Matriz habilidades'!$N$6:$N$49) -> 0.083333333 | L15: — | M15: =SUMPRODUCT('Matriz habilidades'!$E$6:$E$49,'Matriz habilidades'!$O$6:$O$49,'Matriz habilidades'!$P$6:$P$49)/SUMPRODUCT('Matriz habilidades'!$E$6:$E$49,'Matriz habilidades'!$P$6:$P$49) -> 0 | N15: =SUMPRODUCT('Matriz habilidades'!$E$6:$E$49,'Matriz habilidades'!$O$6:$O$49,'Matriz habilidades'!$Q$6:$Q$49)/SUMPRODUCT('Matriz habilidades'!$E$6:$E$49,'Matriz habilidades'!$Q$6:$Q$49) -> 0 | O15: =SUMPRODUCT('Matriz habilidades'!$E$6:$E$49,'Matriz habilidades'!$O$6:$O$49,'Matriz habilidades'!$R$6:$R$49)/SUMPRODUCT('Matriz habilidades'!$E$6:$E$49,'Matriz habilidades'!$R$6:$R$49) -> 0.25
B16: Asesor/a de atención al cliente | C16: =SUMPRODUCT('Matriz habilidades'!$E$6:$E$49,'Matriz habilidades'!$P$6:$P$49,'Matriz habilidades'!$F$6:$F$49)/SUMPRODUCT('Matriz habilidades'!$E$6:$E$49,'Matriz habilidades'!$F$6:$F$49) -> 0.076923077 | D16: =SUMPRODUCT('Matriz habilidades'!$E$6:$E$49,'Matriz habilidades'!$P$6:$P$49,'Matriz habilidades'!$G$6:$G$49)/SUMPRODUCT('Matriz habilidades'!$E$6:$E$49,'Matriz habilidades'!$G$6:$G$49) -> 0.28571429 | E16: =SUMPRODUCT('Matriz habilidades'!$E$6:$E$49,'Matriz habilidades'!$P$6:$P$49,'Matriz habilidades'!$H$6:$H$49)/SUMPRODUCT('Matriz habilidades'!$E$6:$E$49,'Matriz habilidades'!$H$6:$H$49) -> 0 | F16: =SUMPRODUCT('Matriz habilidades'!$E$6:$E$49,'Matriz habilidades'!$P$6:$P$49,'Matriz habilidades'!$I$6:$I$49)/SUMPRODUCT('Matriz habilidades'!$E$6:$E$49,'Matriz habilidades'!$I$6:$I$49) -> 0.30769231 | G16: =SUMPRODUCT('Matriz habilidades'!$E$6:$E$49,'Matriz habilidades'!$P$6:$P$49,'Matriz habilidades'!$J$6:$J$49)/SUMPRODUCT('Matriz habilidades'!$E$6:$E$49,'Matriz habilidades'!$J$6:$J$49) -> 0 | H16: =SUMPRODUCT('Matriz habilidades'!$E$6:$E$49,'Matriz habilidades'!$P$6:$P$49,'Matriz habilidades'!$K$6:$K$49)/SUMPRODUCT('Matriz habilidades'!$E$6:$E$49,'Matriz habilidades'!$K$6:$K$49) -> 0 | I16: =SUMPRODUCT('Matriz habilidades'!$E$6:$E$49,'Matriz habilidades'!$P$6:$P$49,'Matriz habilidades'!$L$6:$L$49)/SUMPRODUCT('Matriz habilidades'!$E$6:$E$49,'Matriz habilidades'!$L$6:$L$49) -> 0.23076923 | J16: =SUMPRODUCT('Matriz habilidades'!$E$6:$E$49,'Matriz habilidades'!$P$6:$P$49,'Matriz habilidades'!$M$6:$M$49)/SUMPRODUCT('Matriz habilidades'!$E$6:$E$49,'Matriz habilidades'!$M$6:$M$49) -> 0.15384615 | K16: =SUMPRODUCT('Matriz habilidades'!$E$6:$E$49,'Matriz habilidades'!$P$6:$P$49,'Matriz habilidades'!$N$6:$N$49)/SUMPRODUCT('Matriz habilidades'!$E$6:$E$49,'Matriz habilidades'!$N$6:$N$49) -> 0 | L16: =SUMPRODUCT('Matriz habilidades'!$E$6:$E$49,'Matriz habilidades'!$P$6:$P$49,'Matriz habilidades'!$O$6:$O$49)/SUMPRODUCT('Matriz habilidades'!$E$6:$E$49,'Matriz habilidades'!$O$6:$O$49) -> 0 | M16: — | N16: =SUMPRODUCT('Matriz habilidades'!$E$6:$E$49,'Matriz habilidades'!$P$6:$P$49,'Matriz habilidades'!$Q$6:$Q$49)/SUMPRODUCT('Matriz habilidades'!$E$6:$E$49,'Matriz habilidades'!$Q$6:$Q$49) -> 0.083333333 | O16: =SUMPRODUCT('Matriz habilidades'!$E$6:$E$49,'Matriz habilidades'!$P$6:$P$49,'Matriz habilidades'!$R$6:$R$49)/SUMPRODUCT('Matriz habilidades'!$E$6:$E$49,'Matriz habilidades'!$R$6:$R$49) -> 0.16666667
B17: Cuidador/a de personas | C17: =SUMPRODUCT('Matriz habilidades'!$E$6:$E$49,'Matriz habilidades'!$Q$6:$Q$49,'Matriz habilidades'!$F$6:$F$49)/SUMPRODUCT('Matriz habilidades'!$E$6:$E$49,'Matriz habilidades'!$F$6:$F$49) -> 0.15384615 | D17: =SUMPRODUCT('Matriz habilidades'!$E$6:$E$49,'Matriz habilidades'!$Q$6:$Q$49,'Matriz habilidades'!$G$6:$G$49)/SUMPRODUCT('Matriz habilidades'!$E$6:$E$49,'Matriz habilidades'!$G$6:$G$49) -> 0.071428571 | E17: =SUMPRODUCT('Matriz habilidades'!$E$6:$E$49,'Matriz habilidades'!$Q$6:$Q$49,'Matriz habilidades'!$H$6:$H$49)/SUMPRODUCT('Matriz habilidades'!$E$6:$E$49,'Matriz habilidades'!$H$6:$H$49) -> 0 | F17: =SUMPRODUCT('Matriz habilidades'!$E$6:$E$49,'Matriz habilidades'!$Q$6:$Q$49,'Matriz habilidades'!$I$6:$I$49)/SUMPRODUCT('Matriz habilidades'!$E$6:$E$49,'Matriz habilidades'!$I$6:$I$49) -> 0.076923077 | G17: =SUMPRODUCT('Matriz habilidades'!$E$6:$E$49,'Matriz habilidades'!$Q$6:$Q$49,'Matriz habilidades'!$J$6:$J$49)/SUMPRODUCT('Matriz habilidades'!$E$6:$E$49,'Matriz habilidades'!$J$6:$J$49) -> 0.16666667 | H17: =SUMPRODUCT('Matriz habilidades'!$E$6:$E$49,'Matriz habilidades'!$Q$6:$Q$49,'Matriz habilidades'!$K$6:$K$49)/SUMPRODUCT('Matriz habilidades'!$E$6:$E$49,'Matriz habilidades'!$K$6:$K$49) -> 0.30769231 | I17: =SUMPRODUCT('Matriz habilidades'!$E$6:$E$49,'Matriz habilidades'!$Q$6:$Q$49,'Matriz habilidades'!$L$6:$L$49)/SUMPRODUCT('Matriz habilidades'!$E$6:$E$49,'Matriz habilidades'!$L$6:$L$49) -> 0.30769231 | J17: =SUMPRODUCT('Matriz habilidades'!$E$6:$E$49,'Matriz habilidades'!$Q$6:$Q$49,'Matriz habilidades'!$M$6:$M$49)/SUMPRODUCT('Matriz habilidades'!$E$6:$E$49,'Matriz habilidades'!$M$6:$M$49) -> 0 | K17: =SUMPRODUCT('Matriz habilidades'!$E$6:$E$49,'Matriz habilidades'!$Q$6:$Q$49,'Matriz habilidades'!$N$6:$N$49)/SUMPRODUCT('Matriz habilidades'!$E$6:$E$49,'Matriz habilidades'!$N$6:$N$49) -> 0.16666667 | L17: =SUMPRODUCT('Matriz habilidades'!$E$6:$E$49,'Matriz habilidades'!$Q$6:$Q$49,'Matriz habilidades'!$O$6:$O$49)/SUMPRODUCT('Matriz habilidades'!$E$6:$E$49,'Matriz habilidades'!$O$6:$O$49) -> 0 | M17: =SUMPRODUCT('Matriz habilidades'!$E$6:$E$49,'Matriz habilidades'!$Q$6:$Q$49,'Matriz habilidades'!$P$6:$P$49)/SUMPRODUCT('Matriz habilidades'!$E$6:$E$49,'Matriz habilidades'!$P$6:$P$49) -> 0.071428571 | N17: — | O17: =SUMPRODUCT('Matriz habilidades'!$E$6:$E$49,'Matriz habilidades'!$Q$6:$Q$49,'Matriz habilidades'!$R$6:$R$49)/SUMPRODUCT('Matriz habilidades'!$E$6:$E$49,'Matriz habilidades'!$R$6:$R$49) -> 0.16666667
B18: Conserje / mantenimiento | C18: =SUMPRODUCT('Matriz habilidades'!$E$6:$E$49,'Matriz habilidades'!$R$6:$R$49,'Matriz habilidades'!$F$6:$F$49)/SUMPRODUCT('Matriz habilidades'!$E$6:$E$49,'Matriz habilidades'!$F$6:$F$49) -> 0.076923077 | D18: =SUMPRODUCT('Matriz habilidades'!$E$6:$E$49,'Matriz habilidades'!$R$6:$R$49,'Matriz habilidades'!$G$6:$G$49)/SUMPRODUCT('Matriz habilidades'!$E$6:$E$49,'Matriz habilidades'!$G$6:$G$49) -> 0 | E18: =SUMPRODUCT('Matriz habilidades'!$E$6:$E$49,'Matriz habilidades'!$R$6:$R$49,'Matriz habilidades'!$H$6:$H$49)/SUMPRODUCT('Matriz habilidades'!$E$6:$E$49,'Matriz habilidades'!$H$6:$H$49) -> 0 | F18: =SUMPRODUCT('Matriz habilidades'!$E$6:$E$49,'Matriz habilidades'!$R$6:$R$49,'Matriz habilidades'!$I$6:$I$49)/SUMPRODUCT('Matriz habilidades'!$E$6:$E$49,'Matriz habilidades'!$I$6:$I$49) -> 0.23076923 | G18: =SUMPRODUCT('Matriz habilidades'!$E$6:$E$49,'Matriz habilidades'!$R$6:$R$49,'Matriz habilidades'!$J$6:$J$49)/SUMPRODUCT('Matriz habilidades'!$E$6:$E$49,'Matriz habilidades'!$J$6:$J$49) -> 0.58333333 | H18: =SUMPRODUCT('Matriz habilidades'!$E$6:$E$49,'Matriz habilidades'!$R$6:$R$49,'Matriz habilidades'!$K$6:$K$49)/SUMPRODUCT('Matriz habilidades'!$E$6:$E$49,'Matriz habilidades'!$K$6:$K$49) -> 0 | I18: =SUMPRODUCT('Matriz habilidades'!$E$6:$E$49,'Matriz habilidades'!$R$6:$R$49,'Matriz habilidades'!$L$6:$L$49)/SUMPRODUCT('Matriz habilidades'!$E$6:$E$49,'Matriz habilidades'!$L$6:$L$49) -> 0 | J18: =SUMPRODUCT('Matriz habilidades'!$E$6:$E$49,'Matriz habilidades'!$R$6:$R$49,'Matriz habilidades'!$M$6:$M$49)/SUMPRODUCT('Matriz habilidades'!$E$6:$E$49,'Matriz habilidades'!$M$6:$M$49) -> 0.30769231 | K18: =SUMPRODUCT('Matriz habilidades'!$E$6:$E$49,'Matriz habilidades'!$R$6:$R$49,'Matriz habilidades'!$N$6:$N$49)/SUMPRODUCT('Matriz habilidades'!$E$6:$E$49,'Matriz habilidades'!$N$6:$N$49) -> 0.16666667 | L18: =SUMPRODUCT('Matriz habilidades'!$E$6:$E$49,'Matriz habilidades'!$R$6:$R$49,'Matriz habilidades'!$O$6:$O$49)/SUMPRODUCT('Matriz habilidades'!$E$6:$E$49,'Matriz habilidades'!$O$6:$O$49) -> 0.27272727 | M18: =SUMPRODUCT('Matriz habilidades'!$E$6:$E$49,'Matriz habilidades'!$R$6:$R$49,'Matriz habilidades'!$P$6:$P$49)/SUMPRODUCT('Matriz habilidades'!$E$6:$E$49,'Matriz habilidades'!$P$6:$P$49) -> 0.14285714 | N18: =SUMPRODUCT('Matriz habilidades'!$E$6:$E$49,'Matriz habilidades'!$R$6:$R$49,'Matriz habilidades'!$Q$6:$Q$49)/SUMPRODUCT('Matriz habilidades'!$E$6:$E$49,'Matriz habilidades'!$Q$6:$Q$49) -> 0.16666667 | O18: —
B20: Cómo se calcula (igual que el motor de Chambea):
B21: Proximidad(A → B) = suma de pesos de las habilidades de B que A también tiene ÷ suma de pesos de todas las habilidades de B.
B22: No es simétrica: A → B puede ser distinto de B → A, porque cada ocupación pide habilidades con pesos distintos. La diagonal (—) es la misma ocupación.
B23: Colores: blanco = no comparten nada · amarillo = comparten algo · verde = muy cercanas.

Sheet En común
A1: Habilidades en común entre ocupaciones
A2: Cuántas de sus 7 habilidades típicas comparten dos ocupaciones (sin pesos). Esta matriz sí es simétrica.
B5: Ocupación | C5: Cajero/a | D5: Vendedor/a de tienda | E5: Reponedor/a y abastecedor/a | F5: Auxiliar administrativo/a | G5: Personal de limpieza | H5: Ayudante de cocina | I5: Mozo/a de restaurante | J5: Auxiliar de almacén | K5: Repartidor/a | L5: Operario/a de producción | M5: Asesor/a de atención al cliente | N5: Cuidador/a de personas | O5: Conserje / mantenimiento
B6: Cajero/a | C6: — | D6: =SUMPRODUCT('Matriz habilidades'!$F$6:$F$49,'Matriz habilidades'!$G$6:$G$49) -> 4 | E6: =SUMPRODUCT('Matriz habilidades'!$F$6:$F$49,'Matriz habilidades'!$H$6:$H$49) -> 0 | F6: =SUMPRODUCT('Matriz habilidades'!$F$6:$F$49,'Matriz habilidades'!$I$6:$I$49) -> 0 | G6: =SUMPRODUCT('Matriz habilidades'!$F$6:$F$49,'Matriz habilidades'!$J$6:$J$49) -> 1 | H6: =SUMPRODUCT('Matriz habilidades'!$F$6:$F$49,'Matriz habilidades'!$K$6:$K$49) -> 0 | I6: =SUMPRODUCT('Matriz habilidades'!$F$6:$F$49,'Matriz habilidades'!$L$6:$L$49) -> 3 | J6: =SUMPRODUCT('Matriz habilidades'!$F$6:$F$49,'Matriz habilidades'!$M$6:$M$49) -> 0 | K6: =SUMPRODUCT('Matriz habilidades'!$F$6:$F$49,'Matriz habilidades'!$N$6:$N$49) -> 2 | L6: =SUMPRODUCT('Matriz habilidades'!$F$6:$F$49,'Matriz habilidades'!$O$6:$O$49) -> 0 | M6: =SUMPRODUCT('Matriz habilidades'!$F$6:$F$49,'Matriz habilidades'!$P$6:$P$49) -> 1 | N6: =SUMPRODUCT('Matriz habilidades'!$F$6:$F$49,'Matriz habilidades'!$Q$6:$Q$49) -> 2 | O6: =SUMPRODUCT('Matriz habilidades'!$F$6:$F$49,'Matriz habilidades'!$R$6:$R$49) -> 1
B7: Vendedor/a de tienda | C7: =SUMPRODUCT('Matriz habilidades'!$G$6:$G$49,'Matriz habilidades'!$F$6:$F$49) -> 4 | D7: — | E7: =SUMPRODUCT('Matriz habilidades'!$G$6:$G$49,'Matriz habilidades'!$H$6:$H$49) -> 1 | F7: =SUMPRODUCT('Matriz habilidades'!$G$6:$G$49,'Matriz habilidades'!$I$6:$I$49) -> 0 | G7: =SUMPRODUCT('Matriz habilidades'!$G$6:$G$49,'Matriz habilidades'!$J$6:$J$49) -> 0 | H7: =SUMPRODUCT('Matriz habilidades'!$G$6:$G$49,'Matriz habilidades'!$K$6:$K$49) -> 0 | I7: =SUMPRODUCT('Matriz habilidades'!$G$6:$G$49,'Matriz habilidades'!$L$6:$L$49) -> 3 | J7: =SUMPRODUCT('Matriz habilidades'!$G$6:$G$49,'Matriz habilidades'!$M$6:$M$49) -> 0 | K7: =SUMPRODUCT('Matriz habilidades'!$G$6:$G$49,'Matriz habilidades'!$N$6:$N$49) -> 1 | L7: =SUMPRODUCT('Matriz habilidades'!$G$6:$G$49,'Matriz habilidades'!$O$6:$O$49) -> 0 | M7: =SUMPRODUCT('Matriz habilidades'!$G$6:$G$49,'Matriz habilidades'!$P$6:$P$49) -> 2 | N7: =SUMPRODUCT('Matriz habilidades'!$G$6:$G$49,'Matriz habilidades'!$Q$6:$Q$49) -> 1 | O7: =SUMPRODUCT('Matriz habilidades'!$G$6:$G$49,'Matriz habilidades'!$R$6:$R$49) -> 0
B8: Reponedor/a y abastecedor/a | C8: =SUMPRODUCT('Matriz habilidades'!$H$6:$H$49,'Matriz habilidades'!$F$6:$F$49) -> 0 | D8: =SUMPRODUCT('Matriz habilidades'!$H$6:$H$49,'Matriz habilidades'!$G$6:$G$49) -> 1 | E8: — | F8: =SUMPRODUCT('Matriz habilidades'!$H$6:$H$49,'Matriz habilidades'!$I$6:$I$49) -> 1 | G8: =SUMPRODUCT('Matriz habilidades'!$H$6:$H$49,'Matriz habilidades'!$J$6:$J$49) -> 1 | H8: =SUMPRODUCT('Matriz habilidades'!$H$6:$H$49,'Matriz habilidades'!$K$6:$K$49) -> 0 | I8: =SUMPRODUCT('Matriz habilidades'!$H$6:$H$49,'Matriz habilidades'!$L$6:$L$49) -> 0 | J8: =SUMPRODUCT('Matriz habilidades'!$H$6:$H$49,'Matriz habilidades'!$M$6:$M$49) -> 4 | K8: =SUMPRODUCT('Matriz habilidades'!$H$6:$H$49,'Matriz habilidades'!$N$6:$N$49) -> 1 | L8: =SUMPRODUCT('Matriz habilidades'!$H$6:$H$49,'Matriz habilidades'!$O$6:$O$49) -> 2 | M8: =SUMPRODUCT('Matriz habilidades'!$H$6:$H$49,'Matriz habilidades'!$P$6:$P$49) -> 0 | N8: =SUMPRODUCT('Matriz habilidades'!$H$6:$H$49,'Matriz habilidades'!$Q$6:$Q$49) -> 0 | O8: =SUMPRODUCT('Matriz habilidades'!$H$6:$H$49,'Matriz habilidades'!$R$6:$R$49) -> 0
B9: Auxiliar administrativo/a | C9: =SUMPRODUCT('Matriz habilidades'!$I$6:$I$49,'Matriz habilidades'!$F$6:$F$49) -> 0 | D9: =SUMPRODUCT('Matriz habilidades'!$I$6:$I$49,'Matriz habilidades'!$G$6:$G$49) -> 0 | E9: =SUMPRODUCT('Matriz habilidades'!$I$6:$I$49,'Matriz habilidades'!$H$6:$H$49) -> 1 | F9: — | G9: =SUMPRODUCT('Matriz habilidades'!$I$6:$I$49,'Matriz habilidades'!$J$6:$J$49) -> 1 | H9: =SUMPRODUCT('Matriz habilidades'!$I$6:$I$49,'Matriz habilidades'!$K$6:$K$49) -> 0 | I9: =SUMPRODUCT('Matriz habilidades'!$I$6:$I$49,'Matriz habilidades'!$L$6:$L$49) -> 0 | J9: =SUMPRODUCT('Matriz habilidades'!$I$6:$I$49,'Matriz habilidades'!$M$6:$M$49) -> 2 | K9: =SUMPRODUCT('Matriz habilidades'!$I$6:$I$49,'Matriz habilidades'!$N$6:$N$49) -> 1 | L9: =SUMPRODUCT('Matriz habilidades'!$I$6:$I$49,'Matriz habilidades'!$O$6:$O$49) -> 1 | M9: =SUMPRODUCT('Matriz habilidades'!$I$6:$I$49,'Matriz habilidades'!$P$6:$P$49) -> 2 | N9: =SUMPRODUCT('Matriz habilidades'!$I$6:$I$49,'Matriz habilidades'!$Q$6:$Q$49) -> 1 | O9: =SUMPRODUCT('Matriz habilidades'!$I$6:$I$49,'Matriz habilidades'!$R$6:$R$49) -> 2
B10: Personal de limpieza | C10: =SUMPRODUCT('Matriz habilidades'!$J$6:$J$49,'Matriz habilidades'!$F$6:$F$49) -> 1 | D10: =SUMPRODUCT('Matriz habilidades'!$J$6:$J$49,'Matriz habilidades'!$G$6:$G$49) -> 0 | E10: =SUMPRODUCT('Matriz habilidades'!$J$6:$J$49,'Matriz habilidades'!$H$6:$H$49) -> 1 | F10: =SUMPRODUCT('Matriz habilidades'!$J$6:$J$49,'Matriz habilidades'!$I$6:$I$49) -> 1 | G10: — | H10: =SUMPRODUCT('Matriz habilidades'!$J$6:$J$49,'Matriz habilidades'!$K$6:$K$49) -> 1 | I10: =SUMPRODUCT('Matriz habilidades'!$J$6:$J$49,'Matriz habilidades'!$L$6:$L$49) -> 0 | J10: =SUMPRODUCT('Matriz habilidades'!$J$6:$J$49,'Matriz habilidades'!$M$6:$M$49) -> 2 | K10: =SUMPRODUCT('Matriz habilidades'!$J$6:$J$49,'Matriz habilidades'!$N$6:$N$49) -> 3 | L10: =SUMPRODUCT('Matriz habilidades'!$J$6:$J$49,'Matriz habilidades'!$O$6:$O$49) -> 2 | M10: =SUMPRODUCT('Matriz habilidades'!$J$6:$J$49,'Matriz habilidades'!$P$6:$P$49) -> 0 | N10: =SUMPRODUCT('Matriz habilidades'!$J$6:$J$49,'Matriz habilidades'!$Q$6:$Q$49) -> 2 | O10: =SUMPRODUCT('Matriz habilidades'!$J$6:$J$49,'Matriz habilidades'!$R$6:$R$49) -> 4
B11: Ayudante de cocina | C11: =SUMPRODUCT('Matriz habilidades'!$K$6:$K$49,'Matriz habilidades'!$F$6:$F$49) -> 0 | D11: =SUMPRODUCT('Matriz habilidades'!$K$6:$K$49,'Matriz habilidades'!$G$6:$G$49) -> 0 | E11: =SUMPRODUCT('Matriz habilidades'!$K$6:$K$49,'Matriz habilidades'!$H$6:$H$49) -> 0 | F11: =SUMPRODUCT('Matriz habilidades'!$K$6:$K$49,'Matriz habilidades'!$I$6:$I$49) -> 0 | G11: =SUMPRODUCT('Matriz habilidades'!$K$6:$K$49,'Matriz habilidades'!$J$6:$J$49) -> 1 | H11: — | I11: =SUMPRODUCT('Matriz habilidades'!$K$6:$K$49,'Matriz habilidades'!$L$6:$L$49) -> 1 | J11: =SUMPRODUCT('Matriz habilidades'!$K$6:$K$49,'Matriz habilidades'!$M$6:$M$49) -> 1 | K11: =SUMPRODUCT('Matriz habilidades'!$K$6:$K$49,'Matriz habilidades'!$N$6:$N$49) -> 1 | L11: =SUMPRODUCT('Matriz habilidades'!$K$6:$K$49,'Matriz habilidades'!$O$6:$O$49) -> 1 | M11: =SUMPRODUCT('Matriz habilidades'!$K$6:$K$49,'Matriz habilidades'!$P$6:$P$49) -> 0 | N11: =SUMPRODUCT('Matriz habilidades'!$K$6:$K$49,'Matriz habilidades'!$Q$6:$Q$49) -> 2 | O11: =SUMPRODUCT('Matriz habilidades'!$K$6:$K$49,'Matriz habilidades'!$R$6:$R$49) -> 0
B12: Mozo/a de restaurante | C12: =SUMPRODUCT('Matriz habilidades'!$L$6:$L$49,'Matriz habilidades'!$F$6:$F$49) -> 3 | D12: =SUMPRODUCT('Matriz habilidades'!$L$6:$L$49,'Matriz habilidades'!$G$6:$G$49) -> 3 | E12: =SUMPRODUCT('Matriz habilidades'!$L$6:$L$49,'Matriz habilidades'!$H$6:$H$49) -> 0 | F12: =SUMPRODUCT('Matriz habilidades'!$L$6:$L$49,'Matriz habilidades'!$I$6:$I$49) -> 0 | G12: =SUMPRODUCT('Matriz habilidades'!$L$6:$L$49,'Matriz habilidades'!$J$6:$J$49) -> 0 | H12: =SUMPRODUCT('Matriz habilidades'!$L$6:$L$49,'Matriz habilidades'!$K$6:$K$49) -> 1 | I12: — | J12: =SUMPRODUCT('Matriz habilidades'!$L$6:$L$49,'Matriz habilidades'!$M$6:$M$49) -> 0 | K12: =SUMPRODUCT('Matriz habilidades'!$L$6:$L$49,'Matriz habilidades'!$N$6:$N$49) -> 1 | L12: =SUMPRODUCT('Matriz habilidades'!$L$6:$L$49,'Matriz habilidades'!$O$6:$O$49) -> 0 | M12: =SUMPRODUCT('Matriz habilidades'!$L$6:$L$49,'Matriz habilidades'!$P$6:$P$49) -> 2 | N12: =SUMPRODUCT('Matriz habilidades'!$L$6:$L$49,'Matriz habilidades'!$Q$6:$Q$49) -> 2 | O12: =SUMPRODUCT('Matriz habilidades'!$L$6:$L$49,'Matriz habilidades'!$R$6:$R$49) -> 0
B13: Auxiliar de almacén | C13: =SUMPRODUCT('Matriz habilidades'!$M$6:$M$49,'Matriz habilidades'!$F$6:$F$49) -> 0 | D13: =SUMPRODUCT('Matriz habilidades'!$M$6:$M$49,'Matriz habilidades'!$G$6:$G$49) -> 0 | E13: =SUMPRODUCT('Matriz habilidades'!$M$6:$M$49,'Matriz habilidades'!$H$6:$H$49) -> 4 | F13: =SUMPRODUCT('Matriz habilidades'!$M$6:$M$49,'Matriz habilidades'!$I$6:$I$49) -> 2 | G13: =SUMPRODUCT('Matriz habilidades'!$M$6:$M$49,'Matriz habilidades'!$J$6:$J$49) -> 2 | H13: =SUMPRODUCT('Matriz habilidades'!$M$6:$M$49,'Matriz habilidades'!$K$6:$K$49) -> 1 | I13: =SUMPRODUCT('Matriz habilidades'!$M$6:$M$49,'Matriz habilidades'!$L$6:$L$49) -> 0 | J13: — | K13: =SUMPRODUCT('Matriz habilidades'!$M$6:$M$49,'Matriz habilidades'!$N$6:$N$49) -> 2 | L13: =SUMPRODUCT('Matriz habilidades'!$M$6:$M$49,'Matriz habilidades'!$O$6:$O$49) -> 3 | M13: =SUMPRODUCT('Matriz habilidades'!$M$6:$M$49,'Matriz habilidades'!$P$6:$P$49) -> 1 | N13: =SUMPRODUCT('Matriz habilidades'!$M$6:$M$49,'Matriz habilidades'!$Q$6:$Q$49) -> 0 | O13: =SUMPRODUCT('Matriz habilidades'!$M$6:$M$49,'Matriz habilidades'!$R$6:$R$49) -> 2
B14: Repartidor/a | C14: =SUMPRODUCT('Matriz habilidades'!$N$6:$N$49,'Matriz habilidades'!$F$6:$F$49) -> 2 | D14: =SUMPRODUCT('Matriz habilidades'!$N$6:$N$49,'Matriz habilidades'!$G$6:$G$49) -> 1 | E14: =SUMPRODUCT('Matriz habilidades'!$N$6:$N$49,'Matriz habilidades'!$H$6:$H$49) -> 1 | F14: =SUMPRODUCT('Matriz habilidades'!$N$6:$N$49,'Matriz habilidades'!$I$6:$I$49) -> 1 | G14: =SUMPRODUCT('Matriz habilidades'!$N$6:$N$49,'Matriz habilidades'!$J$6:$J$49) -> 3 | H14: =SUMPRODUCT('Matriz habilidades'!$N$6:$N$49,'Matriz habilidades'!$K$6:$K$49) -> 1 | I14: =SUMPRODUCT('Matriz habilidades'!$N$6:$N$49,'Matriz habilidades'!$L$6:$L$49) -> 1 | J14: =SUMPRODUCT('Matriz habilidades'!$N$6:$N$49,'Matriz habilidades'!$M$6:$M$49) -> 2 | K14: — | L14: =SUMPRODUCT('Matriz habilidades'!$N$6:$N$49,'Matriz habilidades'!$O$6:$O$49) -> 1 | M14: =SUMPRODUCT('Matriz habilidades'!$N$6:$N$49,'Matriz habilidades'!$P$6:$P$49) -> 0 | N14: =SUMPRODUCT('Matriz habilidades'!$N$6:$N$49,'Matriz habilidades'!$Q$6:$Q$49) -> 2 | O14: =SUMPRODUCT('Matriz habilidades'!$N$6:$N$49,'Matriz habilidades'!$R$6:$R$49) -> 2
B15: Operario/a de producción | C15: =SUMPRODUCT('Matriz habilidades'!$O$6:$O$49,'Matriz habilidades'!$F$6:$F$49) -> 0 | D15: =SUMPRODUCT('Matriz habilidades'!$O$6:$O$49,'Matriz habilidades'!$G$6:$G$49) -> 0 | E15: =SUMPRODUCT('Matriz habilidades'!$O$6:$O$49,'Matriz habilidades'!$H$6:$H$49) -> 2 | F15: =SUMPRODUCT('Matriz habilidades'!$O$6:$O$49,'Matriz habilidades'!$I$6:$I$49) -> 1 | G15: =SUMPRODUCT('Matriz habilidades'!$O$6:$O$49,'Matriz habilidades'!$J$6:$J$49) -> 2 | H15: =SUMPRODUCT('Matriz habilidades'!$O$6:$O$49,'Matriz habilidades'!$K$6:$K$49) -> 1 | I15: =SUMPRODUCT('Matriz habilidades'!$O$6:$O$49,'Matriz habilidades'!$L$6:$L$49) -> 0 | J15: =SUMPRODUCT('Matriz habilidades'!$O$6:$O$49,'Matriz habilidades'!$M$6:$M$49) -> 3 | K15: =SUMPRODUCT('Matriz habilidades'!$O$6:$O$49,'Matriz habilidades'!$N$6:$N$49) -> 1 | L15: — | M15: =SUMPRODUCT('Matriz habilidades'!$O$6:$O$49,'Matriz habilidades'!$P$6:$P$49) -> 0 | N15: =SUMPRODUCT('Matriz habilidades'!$O$6:$O$49,'Matriz habilidades'!$Q$6:$Q$49) -> 0 | O15: =SUMPRODUCT('Matriz habilidades'!$O$6:$O$49,'Matriz habilidades'!$R$6:$R$49) -> 2
B16: Asesor/a de atención al cliente | C16: =SUMPRODUCT('Matriz habilidades'!$P$6:$P$49,'Matriz habilidades'!$F$6:$F$49) -> 1 | D16: =SUMPRODUCT('Matriz habilidades'!$P$6:$P$49,'Matriz habilidades'!$G$6:$G$49) -> 2 | E16: =SUMPRODUCT('Matriz habilidades'!$P$6:$P$49,'Matriz habilidades'!$H$6:$H$49) -> 0 | F16: =SUMPRODUCT('Matriz habilidades'!$P$6:$P$49,'Matriz habilidades'!$I$6:$I$49) -> 2 | G16: =SUMPRODUCT('Matriz habilidades'!$P$6:$P$49,'Matriz habilidades'!$J$6:$J$49) -> 0 | H16: =SUMPRODUCT('Matriz habilidades'!$P$6:$P$49,'Matriz habilidades'!$K$6:$K$49) -> 0 | I16: =SUMPRODUCT('Matriz habilidades'!$P$6:$P$49,'Matriz habilidades'!$L$6:$L$49) -> 2 | J16: =SUMPRODUCT('Matriz habilidades'!$P$6:$P$49,'Matriz habilidades'!$M$6:$M$49) -> 1 | K16: =SUMPRODUCT('Matriz habilidades'!$P$6:$P$49,'Matriz habilidades'!$N$6:$N$49) -> 0 | L16: =SUMPRODUCT('Matriz habilidades'!$P$6:$P$49,'Matriz habilidades'!$O$6:$O$49) -> 0 | M16: — | N16: =SUMPRODUCT('Matriz habilidades'!$P$6:$P$49,'Matriz habilidades'!$Q$6:$Q$49) -> 1 | O16: =SUMPRODUCT('Matriz habilidades'!$P$6:$P$49,'Matriz habilidades'!$R$6:$R$49) -> 1
B17: Cuidador/a de personas | C17: =SUMPRODUCT('Matriz habilidades'!$Q$6:$Q$49,'Matriz habilidades'!$F$6:$F$49) -> 2 | D17: =SUMPRODUCT('Matriz habilidades'!$Q$6:$Q$49,'Matriz habilidades'!$G$6:$G$49) -> 1 | E17: =SUMPRODUCT('Matriz habilidades'!$Q$6:$Q$49,'Matriz habilidades'!$H$6:$H$49) -> 0 | F17: =SUMPRODUCT('Matriz habilidades'!$Q$6:$Q$49,'Matriz habilidades'!$I$6:$I$49) -> 1 | G17: =SUMPRODUCT('Matriz habilidades'!$Q$6:$Q$49,'Matriz habilidades'!$J$6:$J$49) -> 2 | H17: =SUMPRODUCT('Matriz habilidades'!$Q$6:$Q$49,'Matriz habilidades'!$K$6:$K$49) -> 2 | I17: =SUMPRODUCT('Matriz habilidades'!$Q$6:$Q$49,'Matriz habilidades'!$L$6:$L$49) -> 2 | J17: =SUMPRODUCT('Matriz habilidades'!$Q$6:$Q$49,'Matriz habilidades'!$M$6:$M$49) -> 0 | K17: =SUMPRODUCT('Matriz habilidades'!$Q$6:$Q$49,'Matriz habilidades'!$N$6:$N$49) -> 2 | L17: =SUMPRODUCT('Matriz habilidades'!$Q$6:$Q$49,'Matriz habilidades'!$O$6:$O$49) -> 0 | M17: =SUMPRODUCT('Matriz habilidades'!$Q$6:$Q$49,'Matriz habilidades'!$P$6:$P$49) -> 1 | N17: — | O17: =SUMPRODUCT('Matriz habilidades'!$Q$6:$Q$49,'Matriz habilidades'!$R$6:$R$49) -> 2
B18: Conserje / mantenimiento | C18: =SUMPRODUCT('Matriz habilidades'!$R$6:$R$49,'Matriz habilidades'!$F$6:$F$49) -> 1 | D18: =SUMPRODUCT('Matriz habilidades'!$R$6:$R$49,'Matriz habilidades'!$G$6:$G$49) -> 0 | E18: =SUMPRODUCT('Matriz habilidades'!$R$6:$R$49,'Matriz habilidades'!$H$6:$H$49) -> 0 | F18: =SUMPRODUCT('Matriz habilidades'!$R$6:$R$49,'Matriz habilidades'!$I$6:$I$49) -> 2 | G18: =SUMPRODUCT('Matriz habilidades'!$R$6:$R$49,'Matriz habilidades'!$J$6:$J$49) -> 4 | H18: =SUMPRODUCT('Matriz habilidades'!$R$6:$R$49,'Matriz habilidades'!$K$6:$K$49) -> 0 | I18: =SUMPRODUCT('Matriz habilidades'!$R$6:$R$49,'Matriz habilidades'!$L$6:$L$49) -> 0 | J18: =SUMPRODUCT('Matriz habilidades'!$R$6:$R$49,'Matriz habilidades'!$M$6:$M$49) -> 2 | K18: =SUMPRODUCT('Matriz habilidades'!$R$6:$R$49,'Matriz habilidades'!$N$6:$N$49) -> 2 | L18: =SUMPRODUCT('Matriz habilidades'!$R$6:$R$49,'Matriz habilidades'!$O$6:$O$49) -> 2 | M18: =SUMPRODUCT('Matriz habilidades'!$R$6:$R$49,'Matriz habilidades'!$P$6:$P$49) -> 1 | N18: =SUMPRODUCT('Matriz habilidades'!$R$6:$R$49,'Matriz habilidades'!$Q$6:$Q$49) -> 2 | O18: —

Sheet Rutas por oficio
A1: De cada oficio a las demás ocupaciones: de la más cercana a la más lejana
A2: El orden se calculó con los pesos actuales; el % y el nivel se recalculan si cambian los Supuestos. «Comparten» y «Le falta» salen de la Matriz de habilidades.
A4: Oficio de hoy | B4: Puesto | C4: Podría pasar a | D4: Proximidad | E4: Nivel | F4: Habilidades en común | G4: Lo que comparten (similitudes) | H4: Lo que le falta | I4: Demanda del destino en Lima
A5: Cajero/a | B5: 1 Más cercana | C5: Vendedor/a de tienda | D5: =INDEX(Proximidad!$C$6:$O$18,MATCH(A5,Proximidad!$B$6:$B$18,0),MATCH(C5,Proximidad!$C$5:$O$5,0)) -> 0.5 | E5: =IF(D5>=Supuestos!$B$12,"Cercana",IF(D5>=Supuestos!$B$13,"Media","Lejana")) -> Cercana | F5: =INDEX('En común'!$C$6:$O$18,MATCH(A5,'En común'!$B$6:$B$18,0),MATCH(C5,'En común'!$C$5:$O$5,0)) -> 4 | G5: Atención al cliente, Medios de pago, Cobro en caja, Paciencia | H5: Resolver reclamos (logro), Reposición (habilidad), Técnicas de venta (habilidad) | I5: alta
A6: Cajero/a | B6: 2 Más cercana | C6: Mozo/a de restaurante | D6: =INDEX(Proximidad!$C$6:$O$18,MATCH(A6,Proximidad!$B$6:$B$18,0),MATCH(C6,Proximidad!$C$5:$O$5,0)) -> 0.38461538 | E6: =IF(D6>=Supuestos!$B$12,"Cercana",IF(D6>=Supuestos!$B$13,"Media","Lejana")) -> Media | F6: =INDEX('En común'!$C$6:$O$18,MATCH(A6,'En común'!$B$6:$B$18,0),MATCH(C6,'En común'!$C$5:$O$5,0)) -> 3 | G6: Atención al cliente, Paciencia, Cobro en caja | H6: Servicio de mesa (habilidad), Comunicación (habilidad), Trabajo bajo presión (cualidad), Clientes que vuelven (logro) | I6: alta
A7: Cajero/a | B7: 3 Más cercana | C7: Repartidor/a | D7: =INDEX(Proximidad!$C$6:$O$18,MATCH(A7,Proximidad!$B$6:$B$18,0),MATCH(C7,Proximidad!$C$5:$O$5,0)) -> 0.25 | E7: =IF(D7>=Supuestos!$B$12,"Cercana",IF(D7>=Supuestos!$B$13,"Media","Lejana")) -> Media | F7: =INDEX('En común'!$C$6:$O$18,MATCH(A7,'En común'!$B$6:$B$18,0),MATCH(C7,'En común'!$C$5:$O$5,0)) -> 2 | G7: Honestidad, Atención al cliente | H7: Reparto y rutas (habilidad), Puntualidad (cualidad), Manejo de dinero (conocimiento), Resistencia física (cualidad), Pedidos a tiempo (logro) | I7: alta
A8: Cajero/a | B8: 4 | C8: Cuidador/a de personas | D8: =INDEX(Proximidad!$C$6:$O$18,MATCH(A8,Proximidad!$B$6:$B$18,0),MATCH(C8,Proximidad!$C$5:$O$5,0)) -> 0.16666667 | E8: =IF(D8>=Supuestos!$B$12,"Cercana",IF(D8>=Supuestos!$B$13,"Media","Lejana")) -> Lejana | F8: =INDEX('En común'!$C$6:$O$18,MATCH(A8,'En común'!$B$6:$B$18,0),MATCH(C8,'En común'!$C$5:$O$5,0)) -> 2 | G8: Paciencia, Honestidad | H8: Cuidado de personas (habilidad), Higiene de alimentos (conocimiento), Puntualidad (cualidad), Cocina (habilidad), Clientes que vuelven (logro) | I8: media
A9: Cajero/a | B9: 5 | C9: Conserje / mantenimiento | D9: =INDEX(Proximidad!$C$6:$O$18,MATCH(A9,Proximidad!$B$6:$B$18,0),MATCH(C9,Proximidad!$C$5:$O$5,0)) -> 0.083333333 | E9: =IF(D9>=Supuestos!$B$12,"Cercana",IF(D9>=Supuestos!$B$13,"Media","Lejana")) -> Lejana | F9: =INDEX('En común'!$C$6:$O$18,MATCH(A9,'En común'!$B$6:$B$18,0),MATCH(C9,'En común'!$C$5:$O$5,0)) -> 1 | G9: Honestidad | H9: Mantenimiento básico (habilidad), Seguridad en el trabajo (conocimiento), Cumplimiento de normas (cualidad), Puntualidad (cualidad), Registro de datos (habilidad), Ambientes impecables (logro) | I9: media
A10: Cajero/a | B10: 6 | C10: Personal de limpieza | D10: =INDEX(Proximidad!$C$6:$O$18,MATCH(A10,Proximidad!$B$6:$B$18,0),MATCH(C10,Proximidad!$C$5:$O$5,0)) -> 0.083333333 | E10: =IF(D10>=Supuestos!$B$12,"Cercana",IF(D10>=Supuestos!$B$13,"Media","Lejana")) -> Lejana | F10: =INDEX('En común'!$C$6:$O$18,MATCH(A10,'En común'!$B$6:$B$18,0),MATCH(C10,'En común'!$C$5:$O$5,0)) -> 1 | G10: Honestidad | H10: Limpieza y desinfección (habilidad), Productos de limpieza (conocimiento), Seguridad en el trabajo (conocimiento), Puntualidad (cualidad), Resistencia física (cualidad), Ambientes impecables (logro) | I10: media
A11: Cajero/a | B11: 7 | C11: Asesor/a de atención al cliente | D11: =INDEX(Proximidad!$C$6:$O$18,MATCH(A11,Proximidad!$B$6:$B$18,0),MATCH(C11,Proximidad!$C$5:$O$5,0)) -> 0.071428571 | E11: =IF(D11>=Supuestos!$B$12,"Cercana",IF(D11>=Supuestos!$B$13,"Media","Lejana")) -> Lejana | F11: =INDEX('En común'!$C$6:$O$18,MATCH(A11,'En común'!$B$6:$B$18,0),MATCH(C11,'En común'!$C$5:$O$5,0)) -> 1 | G11: Paciencia | H11: Atención telefónica (habilidad), Comunicación (habilidad), Resolver reclamos (logro), Registro de datos (habilidad), Computación básica (habilidad), Detectar necesidades (habilidad) | I11: alta
A12: Cajero/a | B12: 8 | C12: Auxiliar administrativo/a | D12: =INDEX(Proximidad!$C$6:$O$18,MATCH(A12,Proximidad!$B$6:$B$18,0),MATCH(C12,Proximidad!$C$5:$O$5,0)) -> 0 | E12: =IF(D12>=Supuestos!$B$12,"Cercana",IF(D12>=Supuestos!$B$13,"Media","Lejana")) -> Lejana | F12: =INDEX('En común'!$C$6:$O$18,MATCH(A12,'En común'!$B$6:$B$18,0),MATCH(C12,'En común'!$C$5:$O$5,0)) -> 0 | G12: — | H12: Archivo de documentos (habilidad), Registro de datos (habilidad), Computación básica (habilidad), Documentos comerciales (conocimiento), Organización y orden (cualidad), Puntualidad (cualidad), Documentos al día (logro) | I12: media
A13: Cajero/a | B13: 9 | C13: Auxiliar de almacén | D13: =INDEX(Proximidad!$C$6:$O$18,MATCH(A13,Proximidad!$B$6:$B$18,0),MATCH(C13,Proximidad!$C$5:$O$5,0)) -> 0 | E13: =IF(D13>=Supuestos!$B$12,"Cercana",IF(D13>=Supuestos!$B$13,"Media","Lejana")) -> Lejana | F13: =INDEX('En común'!$C$6:$O$18,MATCH(A13,'En común'!$B$6:$B$18,0),MATCH(C13,'En común'!$C$5:$O$5,0)) -> 0 | G13: — | H13: Recepción de mercadería (habilidad), Control de inventario (habilidad), Registro de datos (habilidad), Organización y orden (cualidad), Resistencia física (cualidad), Seguridad en el trabajo (conocimiento), Pedidos a tiempo (logro) | I13: alta
A14: Cajero/a | B14: 10 Más lejana | C14: Ayudante de cocina | D14: =INDEX(Proximidad!$C$6:$O$18,MATCH(A14,Proximidad!$B$6:$B$18,0),MATCH(C14,Proximidad!$C$5:$O$5,0)) -> 0 | E14: =IF(D14>=Supuestos!$B$12,"Cercana",IF(D14>=Supuestos!$B$13,"Media","Lejana")) -> Lejana | F14: =INDEX('En común'!$C$6:$O$18,MATCH(A14,'En común'!$B$6:$B$18,0),MATCH(C14,'En común'!$C$5:$O$5,0)) -> 0 | G14: — | H14: Cocina (habilidad), Higiene de alimentos (conocimiento), Organización del tiempo (habilidad), Trabajo bajo presión (cualidad), Limpieza y desinfección (habilidad), Trabajo en equipo (cualidad), Pedidos a tiempo (logro) | I14: alta
A15: Cajero/a | B15: 11 Más lejana | C15: Operario/a de producción | D15: =INDEX(Proximidad!$C$6:$O$18,MATCH(A15,Proximidad!$B$6:$B$18,0),MATCH(C15,Proximidad!$C$5:$O$5,0)) -> 0 | E15: =IF(D15>=Supuestos!$B$12,"Cercana",IF(D15>=Supuestos!$B$13,"Media","Lejana")) -> Lejana | F15: =INDEX('En común'!$C$6:$O$18,MATCH(A15,'En común'!$B$6:$B$18,0),MATCH(C15,'En común'!$C$5:$O$5,0)) -> 0 | G15: — | H15: Manejo de máquinas (habilidad), Cumplimiento de normas (cualidad), Seguridad en el trabajo (conocimiento), Resistencia física (cualidad), Trabajo en equipo (cualidad), Organización y orden (cualidad), Meta del turno (logro) | I15: media
A16: Cajero/a | B16: 12 Más lejana | C16: Reponedor/a y abastecedor/a | D16: =INDEX(Proximidad!$C$6:$O$18,MATCH(A16,Proximidad!$B$6:$B$18,0),MATCH(C16,Proximidad!$C$5:$O$5,0)) -> 0 | E16: =IF(D16>=Supuestos!$B$12,"Cercana",IF(D16>=Supuestos!$B$13,"Media","Lejana")) -> Lejana | F16: =INDEX('En común'!$C$6:$O$18,MATCH(A16,'En común'!$B$6:$B$18,0),MATCH(C16,'En común'!$C$5:$O$5,0)) -> 0 | G16: — | H16: Reposición (habilidad), Control de inventario (habilidad), Ubicación de productos (conocimiento), Recepción de mercadería (habilidad), Organización y orden (cualidad), Resistencia física (cualidad), Zona siempre abastecida (logro) | I16: alta
... A160: Conserje / mantenimiento | B160: 12 Más lejana | C160: Vendedor/a de tienda | D160: =INDEX(Proximidad!$C$6:$O$18,MATCH(A160,Proximidad!$B$6:$B$18,0),MATCH(C160,Proximidad!$C$5:$O$5,0)) -> 0 | E160: =IF(D160>=Supuestos!$B$12,"Cercana",IF(D160>=Supuestos!$B$13,"Media","Lejana")) -> Lejana | F160: =INDEX('En común'!$C$6:$O$18,MATCH(A160,'En común'!$B$6:$B$18,0),MATCH(C160,'En común'!$C$5:$O$5,0)) -> 0 | G160: — | H160: Atención al cliente (habilidad), Medios de pago (conocimiento), Cobro en caja (habilidad), Paciencia (cualidad), Resolver reclamos (logro), Reposición (habilidad), Técnicas de venta (habilidad) | I160: alta

Sheet Validación
A1: Sustento técnico y mecanismos de validación
A2: Cómo sabemos que dos ocupaciones se relacionan, y cómo lo vamos a comprobar.
A4: # | B4: Mecanismo | C4: Qué comprueba | D4: Estado
A5: 1 | B5: Competencias compartidas (esta matriz) | C5: Dos ocupaciones se relacionan por las habilidades que piden en común, con el perfil de 4 dimensiones del MTPE (conocimiento, habilidad, cualidad, logro). | D5: Hecho
A6: 2 | B6: Pesos por dimensión | C6: Un logro pesa 3, una habilidad o un conocimiento 2 y una cualidad 1: lo más específico y demostrable pesa más que lo genérico. Se pueden cambiar en «Supuestos» para ver si el orden se mantiene (análisis de sensibilidad). | D6: Hecho
A7: 3 | B7: Mismo cálculo que la app | C7: La proximidad de esta hoja usa la misma fórmula del motor de Chambea (calcularCobertura). Hay 15 pruebas automáticas que verifican el motor (ej.: Rosa, cajera → Vendedor/a de tienda; Marleny, limpieza → Conserje). | D7: Hecho
A8: 4 | B8: Contraste con avisos reales | C8: Los «alias» de cada ocupación salen de cómo se publican los avisos (ej.: Vendedor/a de tienda = Asesor/a de ventas). Se revisa que los avisos de la ocupación destino pidan las habilidades que la matriz dice que comparten. | D8: Parcial
A9: 5 | B9: Estándares de competencia del MTPE | C9: Reemplazar las 7 habilidades de ejemplo de cada ocupación por las unidades de competencia oficiales. La matriz se recalcula sola al cambiar los datos. | D9: Pendiente
A10: 6 | B10: Validación con expertos (asesores de Centros de Empleo) | C10: Los asesores califican si cada transición propuesta es realista (tabla de abajo). Si una ruta cercana sale mal calificada, se revisan sus habilidades o pesos. | D10: Pendiente
A11: 7 | B11: Demanda real (EDO 2026) | C11: Que la ocupación destino tenga demanda en la región. Hoy la demanda es de ejemplo. | D11: Pendiente
A12: 8 | B12: Transiciones observadas | C12: Con datos de colocaciones (Empleos Perú / Centros de Empleo), comprobar que las personas sí pasan entre las ocupaciones que la matriz marca como cercanas. | D12: Futuro
A15: Plantilla de validación con asesores
A16: Para llenar: celdas amarillas. Calificación de 1 (nada realista) a 5 (muy realista; es común que la gente pase así). Ejemplo de respuesta: 4 — «Sí, muchas cajeras pasan a ventas en la misma tienda».
A17: Oficio de hoy | B17: Podría pasar a | C17: Proximidad | D17: ¿Es realista? (1–5) | E17: Comentario del asesor | F17: Nombre del asesor y Centro de Empleo
A18: Cajero/a | B18: Vendedor/a de tienda | C18: =INDEX(Proximidad!$C$6:$O$18,MATCH(A18,Proximidad!$B$6:$B$18,0),MATCH(B18,Proximidad!$C$5:$O$5,0)) -> 0.5
A19: Cajero/a | B19: Mozo/a de restaurante | C19: =INDEX(Proximidad!$C$6:$O$18,MATCH(A19,Proximidad!$B$6:$B$18,0),MATCH(B19,Proximidad!$C$5:$O$5,0)) -> 0.38461538
A20: Vendedor/a de tienda | B20: Cajero/a | C20: =INDEX(Proximidad!$C$6:$O$18,MATCH(A20,Proximidad!$B$6:$B$18,0),MATCH(B20,Proximidad!$C$5:$O$5,0)) -> 0.53846154
A21: Vendedor/a de tienda | B21: Mozo/a de restaurante | C21: =INDEX(Proximidad!$C$6:$O$18,MATCH(A21,Proximidad!$B$6:$B$18,0),MATCH(B21,Proximidad!$C$5:$O$5,0)) -> 0.38461538
A22: Reponedor/a y abastecedor/a | B22: Auxiliar de almacén | C22: =INDEX(Proximidad!$C$6:$O$18,MATCH(A22,Proximidad!$B$6:$B$18,0),MATCH(B22,Proximidad!$C$5:$O$5,0)) -> 0.46153846
A23: Reponedor/a y abastecedor/a | B23: Operario/a de producción | C23: =INDEX(Proximidad!$C$6:$O$18,MATCH(A23,Proximidad!$B$6:$B$18,0),MATCH(B23,Proximidad!$C$5:$O$5,0)) -> 0.18181818
A24: Auxiliar administrativo/a | B24: Asesor/a de atención al cliente | C24: =INDEX(Proximidad!$C$6:$O$18,MATCH(A24,Proximidad!$B$6:$B$18,0),MATCH(B24,Proximidad!$C$5:$O$5,0)) -> 0.28571429
A25: Auxiliar administrativo/a | B25: Conserje / mantenimiento | C25: =INDEX(Proximidad!$C$6:$O$18,MATCH(A25,Proximidad!$B$6:$B$18,0),MATCH(B25,Proximidad!$C$5:$O$5,0)) -> 0.25
A26: Personal de limpieza | B26: Conserje / mantenimiento | C26: =INDEX(Proximidad!$C$6:$O$18,MATCH(A26,Proximidad!$B$6:$B$18,0),MATCH(B26,Proximidad!$C$5:$O$5,0)) -> 0.58333333
A27: Personal de limpieza | B27: Operario/a de producción | C27: =INDEX(Proximidad!$C$6:$O$18,MATCH(A27,Proximidad!$B$6:$B$18,0),MATCH(B27,Proximidad!$C$5:$O$5,0)) -> 0.27272727
A28: Ayudante de cocina | B28: Cuidador/a de personas | C28: =INDEX(Proximidad!$C$6:$O$18,MATCH(A28,Proximidad!$B$6:$B$18,0),MATCH(B28,Proximidad!$C$5:$O$5,0)) -> 0.33333333
A29: Ayudante de cocina | B29: Repartidor/a | C29: =INDEX(Proximidad!$C$6:$O$18,MATCH(A29,Proximidad!$B$6:$B$18,0),MATCH(B29,Proximidad!$C$5:$O$5,0)) -> 0.25
... A43: Conserje / mantenimiento | B43: Auxiliar de almacén | C43: =INDEX(Proximidad!$C$6:$O$18,MATCH(A43,Proximidad!$B$6:$B$18,0),MATCH(B43,Proximidad!$C$5:$O$5,0)) -> 0.30769231
A45: Promedio de las calificaciones | D45: =IFERROR(AVERAGE(D18:D43),"Sin datos aún") -> Sin datos aún
